Workbook
Name _9000_Titolare_Effettivo_Cliente_1: #REF!
Name _90Imprese: 'Imprese_File clean'!$A$2:$V$12
Name _90Imprese: 'Imprese_File completo'!$A$2:$V$1833
Name _90LegaliRappresentanti: LegaliRappresentanti!$B$1:$Q$1906
Name Agric_20131128_114925: #REF!
Name Dati: #REF!
Name FARNELL: #REF!
Name Fiorini1: #REF!
Name Fiorini2: #REF!
Name MAROTTA: #REF!

Sheet Imprese_File completo
A1: DATI SOCIETA' | X1: DATI RAPPRESENTANTE LEGALE | AM1: CONTATTI
A2: 99 | B2: RAGIONE SOCIALE | C2: _PIVA | D2: _CF | E2: SEDE | F2: Posizione incrociata | G2: Posizione Duplicata | H2: Crif Number | I2: Denominazione | J2: Partita Iva | K2: REA | L2: CCIAA | M2: Codice fiscale | N2: Indirizzo | O2: Cap | P2: Comune | Q2: Frazione | R2: Provincia | S2: Regione | T2: Stato Impresa Cribis | U2: Natura giuridica | V2: Tipo natura giuridica | X2: Cognome Esponente | Y2: Nome Esponente | Z2: Sesso | AA2: Data di nascita | AB2: Provincia di Nascita | AC2: Comune di Nascita | AD2: Nazione di Nascita | AE2: Cittadinanza | AF2: Indirizzo | AG2: CAP | AH2: Comune | AI2: Provincia | AJ2: Frazione | AK2: Altre indicazioni | AL2: Nazione | AM2: Telefono | AN2: Email | AO2: PEC
A3: 99008921 | B3: LOMBARDO FRANCESCO | C3: 00125710863 | D3: LMBFNC54T28E536A | E3: CORSO UMBERTO 466/A - 94013 LEONFORTE EN | F3: Y | H3: ITDE420E04S0001 | I3: LOMBARDO FRANCESCO | J3: 00125710863 | K3: 30055 | L3: EN | M3: LMBFNC54T28E536A | N3: CORSO UMBERTO I 466/A | O3: 94013 | P3: LEONFORTE | R3: EN | S3: SICILIA | T3: Attiva | U3: IMPRESA INDIVIDUALE | V3: IMPRESE INDIVIDUALI | X3: LOMBARDO | Y3: FRANCESCO | Z3: M | AA3: 28/12/1954 | AB3: EN | AC3: LEONFORTE | AD3: IT | AE3: 0 | AF3: CORSO UMBERTO 564 | AG3: 94013 | AH3: LEONFORTE | AI3: EN | AJ3: 0 | AK3: 0 | AL3: IT | AM3: 0935903233 - 3200804175 GI | AN3: pino.lom88@gmail.com; | AO3: -
A4: 99000087 | B4: TABACCHERIA FONTANADI URIA MULLONI | C4: 00186950317 | D4: RMLNNL60M61E098K | E4: Via P. Signorini 12 - 34170 Gorizia GO | F4: Y | H4: ITAC850C00S0001 | I4: TABACCHERIA FONTANA DI URIA MULLONI ANTONELLA | J4: 00186950317 | K4: 49689 | L4: GO | M4: RMLNNL60M61E098K | N4: VIA SIGNORINI PAOLO 12 | O4: 34170 | P4: GORIZIA | R4: GO | S4: FRIULI-VENEZIA GIULIA | T4: Attiva | U4: IMPRESA INDIVIDUALE | V4: IMPRESE INDIVIDUALI | X4: URIA MULLONI | Y4: ANTONELLA | Z4: F | AA4: 21/08/1960 | AB4: GO | AC4: GORIZIA | AD4: IT | AE4: 0 | AF4: VIA GRADISCA 14 | AG4: 34070 | AH4: MARIANO DEL FRIULI | AI4: GO | AJ4: 0 | AK4: 0 | AL4: 0 | AM4: 048122125 - 3483419322 | AN4: xshana@libero.it; | AO4: -
A5: 99000094 | B5: IOVINO ETTORE CIRORIV. GENERI MONOP | C5: 00211620943 | D5: VNITRC61R14E335C | E5: Via Tedeschi 19 - 86170 Isernia IS | F5: Y | H5: ITF20D000CS0001 | I5: IOVINO ETTORE CIRO | J5: 00211620943 | K5: 23271 | L5: IS | M5: VNITRC61R14E335C | N5: VIA GIULIO TEDESCHI | O5: 86170 | P5: ISERNIA | R5: IS | S5: MOLISE | T5: Attiva | U5: IMPRESA INDIVIDUALE | V5: IMPRESE INDIVIDUALI | X5: IOVINO | Y5: ETTORE CIRO | Z5: M | AA5: 14/10/1961 | AB5: IS | AC5: ISERNIA | AD5: IT | AE5: 0 | AF5: VIA TOSCANINI 14 | AG5: 86170 | AH5: ISERNIA | AI5: IS | AJ5: 0 | AK5: 0 | AL5: 0 | AM5: 0865411908 - 3291413260 | AN5: ettoreciro.iovino1@tin.it; | AO5: -
A6: 99014497 | B6: FABIANO VITO | C6: 00235220563 | D6: FBNVTT45M02B776Y | E6: REPUBBLICA - 01023 BOLSENA | F6: Y | H6: IT9ECE0302S0001 | J6: 00235220563 | K6: 57730 | L6: VT | M6: FBNVTI45M02B776Y | T6: Cessata favorevole | U6: IMPRESA INDIVIDUALE | V6: IMPRESE INDIVIDUALI | X6: - | Y6: - | Z6: - | AA6: - | AB6: - | AC6: - | AD6: - | AE6: - | AF6: - | AG6: - | AH6: - | AI6: - | AJ6: - | AK6: - | AL6: - | AM6: 3202467716 | AN6: VANNI.TUSCIA@GMAIL.COM; | AO6: -
A7: 99015296 | B7: ALTOBELLO VINCENZA | C7: 00245590799 | D7: LTBVCN43L59C352T | E7: LE V.GATTOLEO/ - 88100 CATANZARO | F7: Y | H7: IT9321010AS0001 | I7: ALTOBELLO VINCENZA | J7: 00245590799 | K7: 75377 | L7: CZ | M7: LTBVCN43L59C352T | N7: VIALE VINCENZO GATTOLEO 20 | O7: 88100 | P7: CATANZARO | R7: CZ | S7: CALABRIA | T7: Attiva | U7: IMPRESA INDIVIDUALE | V7: IMPRESE INDIVIDUALI | X7: ALTOBELLO | Y7: VINCENZA | Z7: F | AA7: 19/07/1943 | AB7: CZ | AC7: CATANZARO | AD7: IT | AE7: 0 | AF7: VIALE VINCENZO GATTOLEO 20 | AG7: 88100 | AH7: CATANZARO | AI7: CZ | AJ7: 0 | AK7: 0 | AL7: 0 | AM7: 3336263880 | AN7: vincenzaaltobello@gmail.com; | AO7: -
A8: 99000567 | B8: S.A.M.A.C. DI ERMANNO MORI & C. SNC | C8: 00410540439 | D8: 00410540439 | E8: Contrada Asola 24 - 62012 Civitanova Marche MC | F8: Y | H8: IT6389090DS0001 | I8: S.A.M.A.C. DI MORI ERMANNO E FRATELLI SNC | J8: 00410540439 | K8: 90988 | L8: MC | M8: 00410540439 | N8: CONTRADA ASOLA 24 | O8: 62012 | P8: CIVITANOVA MARCHE | R8: MC | S8: MARCHE | T8: Attiva | U8: SOCIETA' IN NOME COLLETTIVO | V8: SOCIETA' DI PERSONE | X8: MORI | Y8: ALESSANDRA | Z8: F | AA8: 10/07/1966 | AB8: RM | AC8: ROMA | AD8: IT | AE8: 0 | AF8: VIA AURORA 67 | AG8: 62012 | AH8: CIVITANOVA MARCHE | AI8: MC | AJ8: 0 | AK8: 0 | AL8: IT | AM8: 07331871624 - 3282696668 PA | AN8: info@ippocivitanova.it; | AO8: -
A9: 99013241 | B9: BAR CENTRALE S.N.C. DEI FRATELLI SILVANO E MARIO GROSSI | C9: 00429820673 | D9: 00429820673 | E9: PIAZZA DELLA LIBERTA' 15, 64025, PINETO (TE) | F9: Y | H9: IT788F0704S0001 | I9: BAR CENTRALE S.N.C. DEI FRATELLI SILVANO E MARIO GROSSI | J9: 00429820673 | K9: 75112 | L9: TE | M9: 00429820673 | N9: PIAZZA DELLA LIBERTA' 13 | O9: 64025 | P9: PINETO | R9: TE | S9: ABRUZZO | T9: Attiva | U9: SOCIETA' IN NOME COLLETTIVO | V9: SOCIETA' DI PERSONE | X9: GROSSI | Y9: ALEXANDER | Z9: M | AA9: 09/06/1987 | AB9: TE | AC9: ATRI | AD9: 0 | AE9: 0 | AF9: VIA DE LITIO 4 | AG9: 64025 | AH9: PINETO | AI9: TE | AJ9: 0 | AK9: 0 | AL9: IT | AM9: 0859492441 | AN9: barcentrale1985@yahoo.it; | AO9: -
A10: 99015559 | B10: PERITO ROSA | C10: 00433790797 | D10: prtrso47e56c352l | E10: LUNGOMARE - 88100 CATANZARO | F10: Y | H10: ITB14E050BS0001 | I10: PERITO ROSA | J10: 00433790797 | K10: 150509 | L10: CZ | M10: PRTRSO47E56C352L | N10: VIA LUNGOMARE STEFANO PUGLIESE 239-245 | O10: 88100 | P10: CATANZARO | R10: CZ | S10: CALABRIA | T10: Attiva | U10: IMPRESA INDIVIDUALE | V10: IMPRESE INDIVIDUALI | X10: PERITO | Y10: ROSA | Z10: F | AA10: 16/05/1947 | AB10: CZ | AC10: CATANZARO | AD10: IT | AE10: 0 | AF10: VIA LUNGOMARE 271 LIDO | AG10: 88100 | AH10: CATANZARO | AI10: CZ | AJ10: 0 | AK10: 0 | AL10: 0 | AM10: - | AN10: stefanofebbraro@alice.it; | AO10: -
A11: 99004992 | B11: BAR STAZIONE SAS DI INTELLINI GIANN | C11: 00593580673 | D11: 00593580673 | E11: PIAZZALE STAZIONE FF.SS. - 64026 ROSETO DEGLI ABRUZZI TE | F11: Y | H11: IT9FAD0C0CS0001 | I11: BAR STAZIONE SAS DI INTELLINI GIANNI & C. | J11: 00593580673 | K11: 82604 | L11: TE | M11: 00593580673 | N11: PIAZZALE STAZIONE FF.SS. SNC | O11: 64026 | P11: ROSETO DEGLI ABRUZZI | R11: TE | S11: ABRUZZO | T11: Attiva | U11: SOCIETA' IN ACCOMANDITA SEMPLICE | V11: SOCIETA' DI PERSONE | X11: INTELLINI | Y11: GIANNI | Z11: M | AA11: 03/02/1973 | AB11: TE | AC11: ATRI | AD11: IT | AE11: 0 | AF11: VIA SAVINI 9 | AG11: 64026 | AH11: ROSETO DEGLI ABRUZZI | AI11: TE | AJ11: 0 | AK11: 0 | AL11: 0 | AM11: 0858992198 - 3287051039 GI | AN11: barstazi2@tiscali.it; | AO11: -
A12: 99005660 | B12: MASI CATERINA | C12: 00662080829 | D12: MSACRN44A60G543H | E12: VIA VIII MARZO 8 Piana degli Albanesi (PA), | F12: Y | H12: ITE5060203S0001 | I12: MASI CATERINA | J12: 00662080829 | K12: 193675 | L12: PA | M12: MSACRN44A60G543H | N12: VIALE VIII MARZO 19/21 | O12: 90037 | P12: PIANA DEGLI ALBANESI | R12: PA | S12: SICILIA | T12: Attiva | U12: IMPRESA INDIVIDUALE | V12: IMPRESE INDIVIDUALI | X12: MASI | Y12: CATERINA | Z12: F | AA12: 20/01/1944 | AB12: PA | AC12: PIANA DEGLI ALBANESI | AD12: IT | AE12: 0 | AF12: VIA SCHIADA' 17 | AG12: 90037 | AH12: PIANA DEGLI ALBANESI | AI12: PA | AJ12: 0 | AK12: 0 | AL12: 0 | AM12: 3283363212 - 0918930815 | AN12: caterina.masi@tiscali.it; dgiuseppe1979@libero.it | AO12: -
A13: 99014418 | B13: F.LLI IAPALUCCI S.N.C. DI IAPALUCCI MAURIZIO E IAPALUCCI MARIA GIUSEPPINA | C13: 00679950709 | D13: 00679950709 | E13: UMBERTO I - 86015 JELSI | F13: Y | H13: IT49800404S0001 | I13: F.LLI IAPALUCCI SNC DI IAPALUCCI MAURIZIO E IAPALUCCI MARIA GI USEPPINA | J13: 00679950709 | K13: 74452 | L13: CB | M13: 00679950709 | N13: PIAZZA UMBERTO I 22 | O13: 86015 | P13: JELSI | R13: CB | S13: MOLISE | T13: Attiva | U13: SOCIETA' IN NOME COLLETTIVO | V13: SOCIETA' DI PERSONE | X13: IAPALUCCI | Y13: MARIA GIUSEPPPINA | Z13: F | AA13: 11/07/1960 | AB13: CB | AC13: JELSI | AD13: IT | AE13: 0 | AF13: PIAZZA UMBERTO I 51 | AG13: 86015 | AH13: JELSI | AI13: CB | AJ13: 0 | AK13: 0 | AL13: IT | AM13: 0874710355 | AN13: iapalucci1986@gmail.com; | AO13: -
A14: 99000366 | B14: SCACCO NANDO | C14: 00712611003 | D14: SCCNND56L25L182N | E14: PIAZZALE MONSIGNOR GIUSEPPE CASC 15 - 00010 POLI RM | F14: Y | H14: ITB62C040CS0001 | I14: SCACCO NANDO | J14: 00712611003 | K14: 718153 | L14: RM | M14: SCCNND56L25L182N | N14: PIAZZA MONSIGNOR GIUSEPPE CASCIOLI 15 | O14: 00010 | P14: POLI | R14: RM | S14: LAZIO | T14: Attiva | U14: IMPRESA INDIVIDUALE | V14: IMPRESE INDIVIDUALI | X14: Scacco | Y14: Nando | Z14: M | AA14: 25/07/1956 | AB14: RM | AC14: TIVOLI | AD14: IT | AE14: 0 | AF14: VIA ROMA 25 | AG14: 00010 | AH14: POLI | AI14: RM | AJ14: 0 | AK14: 0 | AL14: 0 | AM14: 069551522 - 3387228585 | AN14: barfratelliscacco@gmail.com; | AO14: -
A15: 99000374 | B15: GAMBUTI ROMEO | C15: 00729120402 | D15: -- | E15: VIA RONCI 2 - 47833 MORCIANO DI ROMAGNA | F15: Y | H15: ITEAA80D0ES0001 | J15: 00729120402 | K15: 177058 | L15: RN | M15: GMBRMO43E22E278J | T15: Cessata favorevole | U15: IMPRESA INDIVIDUALE | V15: IMPRESE INDIVIDUALI | X15: - | Y15: - | Z15: - | AA15: - | AB15: - | AC15: - | AD15: - | AE15: - | AF15: - | AG15: - | AH15: - | AI15: - | AJ15: - | AK15: - | AL15: - | AM15: 0541989051 - 3920667006 | AN15: gabrielegambuti@virgilio.it; | AO15: -
A16: 99000387 | B16: PIETRINI UGO | C16: 00757420559 | D16: PTRGUO67T28L814H | E16: VIA CAPITONESE 9 - 05036 NARNI TR | F16: Y | H16: ITD98E0F0DS0001 | I16: PIETRINI UGO | J16: 00757420559 | K16: 78174 | L16: TR | M16: PTRGUO67T28L814H | N16: VIA CAPITONESE 9 | O16: 05035 | P16: NARNI | R16: TR | S16: UMBRIA | T16: Attiva | U16: IMPRESA INDIVIDUALE | V16: IMPRESE INDIVIDUALI | X16: PIETRINI | Y16: UGO | Z16: M | AA16: 28/12/1967 | AB16: VT | AC16: VETRALLA | AD16: IT | AE16: 0 | AF16: LOCALITA' VALLEANTICA SNC | AG16: 05029 | AH16: SAN GEMINI | AI16: TR | AJ16: 0 | AK16: 0 | AL16: IT | AM16: 0744751210 - 3478035369 | AN16: pietri14@ugopietrin.191.it; ugo.p@alice.it | AO16: -
A17: 99009470 | B17: BETTINI DI BETTINI MILENA E STUCCHI ROMANO & C. SNC | C17: 00864880968 | D17: 00864880968 | E17: VIA ROMA 21 - 20040 CAVENAGO DI BRIANZA MI | F17: Y | H17: IT8624000CS0001 | I17: BETTINI DI BETTINI MILENA E STUCCHI ROMANO & C. SNC | J17: 00864880968 | K17: 1169862 | L17: MB | M17: 07605360150 | N17: VIA ROMA 21 | O17: 20040 | P17: CAVENAGO DI BRIANZA | R17: MB | S17: LOMBARDIA | T17: Attiva | U17: SOCIETA' IN NOME COLLETTIVO | V17: SOCIETA' DI PERSONE | X17: BETTINI | Y17: MILENA | Z17: F | AA17: 17/02/1964 | AB17: MB | AC17: VIMERCATE | AD17: IT | AE17: 0 | AF17: VIA ALESSANDRO MANZONI 32 | AG17: 20873 | AH17: CAVENAGO DI BRIANZA | AI17: MB | AJ17: 0 | AK17: 0 | AL17: 0 | AM17: 029501460 | AN17: romano.stucchi@tiscali.it; | AO17: -
A18: 99014738 | B18: BAR PIZZERIA DI FALASCONI E ROSATI | C18: 00884570417 | D18: 00884570417 | E18: CORSO GIOVANNI XXIII 35 61026 PIANDIMELETO (PU) | F18: Y | H18: IT788B0A0ES0001 | I18: FALASCONI E ROSATI SNC | J18: 00884570417 | K18: 93409 | L18: PS | M18: 00884570417 | N18: CORSO GIOVANNI XXIII 35 | O18: 61026 | P18: PIANDIMELETO | R18: PU | S18: MARCHE | T18: Attiva | U18: SOCIETA' IN NOME COLLETTIVO | V18: SOCIETA' DI PERSONE | X18: FALASCONI | Y18: ANTONIO | Z18: M | AA18: 22/12/1961 | AB18: PU | AC18: APECCHIO | AD18: IT | AE18: 0 | AF18: VIA SANT' ANTONIO 46 | AG18: 61026 | AH18: PIANDIMELETO | AI18: PU | AJ18: CASE SPARSE | AK18: 0 | AL18: IT | AM18: - | AN18: ROSALIAROSALIA381@GMAIL.COM; | AO18: -
A19: 99004421 | B19: MANUSHIDI PARADISO LOREDANA | C19: 00887590628 | D19: PRDLDN60L50G631D | E19: PIAZZA S.S. ANNUNZIATA 16 - 82020 PIETRELCINA BN | F19: Y | H19: IT4C07090FS0001 | I19: MANUSHI DI PARADISO LOREDANA | J19: 00887590628 | K19: 69417 | L19: BN | M19: PRDLDN60L50G631D | N19: PIAZZA SANTISSIMA ANNUNZIATA 16 | O19: 82020 | P19: PIETRELCINA | R19: BN | S19: CAMPANIA | T19: Attiva | U19: IMPRESA INDIVIDUALE | V19: IMPRESE INDIVIDUALI | X19: PARADISO | Y19: LOREDANA | Z19: F | AA19: 10/07/1960 | AB19: BN | AC19: PIETRELCINA | AD19: IT | AE19: 0 | AF19: 0 | AG19: 82020 | AH19: PIETRELCINA | AI19: BN | AJ19: 0 | AK19: 0 | AL19: 0 | AM19: 0824991031 - 3475933994 | AN19: lparadiso60@gmail.com; | AO19: -
A20: 99013429 | B20: LAGROTTERIA MARIA ANTONIETTA | C20: 00930240791 | D20: LGRMNT62R67F537Z | E20: VIA N.A.SILVAGGIO SNC, 89843, MAIERATO (VV) | F20: Y | H20: IT77450A0AS0001 | I20: LAGROTTERIA MARIA ANTONIETTA | J20: 00930240791 | K20: 144497 | L20: VV | M20: LGRMNT62R67F537Z | N20: VIA N.A.SILVAGGIO SNC | O20: 89843 | P20: MAIERATO | R20: VV | S20: CALABRIA | T20: Attiva | U20: IMPRESA INDIVIDUALE | V20: IMPRESE INDIVIDUALI | X20: LAGROTTERIA | Y20: MARIA ANTONIETTA | Z20: F | AA20: 27/10/1962 | AB20: VV | AC20: VIBO VALENTIA | AD20: IT | AE20: 0 | AF20: VIA MARTELLITO SNC | AG20: 89843 | AH20: MAIERATO | AI20: VV | AJ20: 0 | AK20: 0 | AL20: 0 | AM20: - | AN20: tabacchi.lagrotteria@gmail.com; | AO20: -
A21: 99013876 | B21: LA GARUFFA DI WU XIAOE | C21: 00950430140 | D21: WUXXIA83R50Z210V | E21: NAZIONALE - 23013 COSIO VALTELLINO | F21: Y | H21: ITEDE50201S0001 | I21: BAR LA GARUFFA DI WU XIAOE | J21: 00950430140 | K21: 72172 | L21: SO | M21: WUXXIA83R50Z210V | N21: VIA STATALE 57 | O21: 23013 | P21: COSIO VALTELLINO | R21: SO | S21: LOMBARDIA | T21: Attiva | U21: IMPRESA INDIVIDUALE | V21: IMPRESE INDIVIDUALI | X21: WU | Y21: XIAOE | Z21: F | AA21: 10/10/1983 | AB21: E | AC21: CINA | AD21: CN | AE21: CINA | AF21: VIA ROMA 45 | AG21: 23013 | AH21: COSIO VALTELLINO | AI21: SO | AJ21: 0 | AK21: 0 | AL21: IT | AM21: 3883410286 - 3319794575 | AN21: haoxin.mercatone@hotmail.it; | AO21: -
A22: 99013286 | B22: BIANCHINI CESARE | C22: 00952320141 | D22: BNCCSR72R21A787Q | E22: VIA V ALPINI 151, 23017, MORBEGNO (SO) | F22: Y | H22: IT61E50206S0001 | I22: BIANCHINI CESARE | J22: 00952320141 | K22: 71774 | L22: SO | M22: BNCCSR72R21A787Q | N22: VIA V ALPINI 132 | O22: 23017 | P22: MORBEGNO | R22: SO | S22: LOMBARDIA | T22: Attiva | U22: IMPRESA INDIVIDUALE | V22: IMPRESE INDIVIDUALI | X22: BIANCHINI | Y22: CESARE | Z22: M | AA22: 21/10/1972 | AB22: SO | AC22: BERBENNO DI VALTELLINA | AD22: IT | AE22: 0 | AF22: VIA CARLO FABANI 18 | AG22: 23017 | AH22: MORBEGNO | AI22: SO | AJ22: 0 | AK22: 0 | AL22: IT | AM22: 0342614618 - 3479002454 | AN22: bianchini.cesare@gmail.com; | AO22: -
A23: 99013644 | B23: CAPURSO GIOVANNI | C23: 00969410588 | D23: CPRGNN48B22A883V | E23: ROSSINI CARLO CONTI - 00147 ROMA | F23: Y | H23: IT64230502S0001 | I23: CAPURSO GIOVANNI | J23: 00969410588 | K23: 339901 | L23: RM | M23: CPRGNN48B22A883V | N23: VIA CARLO CONTI ROSSINI 9/11 | O23: 00147 | P23: ROMA | R23: RM | S23: LAZIO | T23: Attiva | U23: IMPRESA INDIVIDUALE | V23: IMPRESE INDIVIDUALI | X23: CAPURSO | Y23: GIOVANNI | Z23: M | AA23: 22/02/1948 | AB23: BT | AC23: BISCEGLIE | AD23: IT | AE23: 0 | AF23: VIA CARLO CONTI ROSSINI 26 | AG23: 00147 | AH23: ROMA | AI23: RM | AJ23: 0 | AK23: 0 | AL23: IT | AM23: 0651606306 - 3383609906 | AN23: giovanni.capurso48@gmail.com; | AO23: -
A24: 99014524 | B24: DI FRANCO MIRCO | C24: 00974350944 | D24: DFRMRC92H19C096B | E24: DELLA REPUBBLICA - 86087 RIONERO SANNITICO | F24: Y | H24: IT7C500909S0001 | I24: DI FRANCO MIRCO | J24: 00974350944 | K24: 208314 | L24: IS | M24: DFRMRC92H19C096B | N24: PIAZZA DELLA REPUBBLICA SNC | O24: 86087 | P24: RIONERO SANNITICO | R24: IS | S24: MOLISE | T24: Attiva | U24: IMPRESA INDIVIDUALE | V24: IMPRESE INDIVIDUALI | X24: DI FRANCO | Y24: MIRCO | Z24: M | AA24: 19/06/1992 | AB24: AQ | AC24: CASTEL DI SANGRO | AD24: 0 | AE24: 0 | AF24: CONTRADA MONTALTO 3 | AG24: 86087 | AH24: RIONERO SANNITICO | AI24: IS | AJ24: 0 | AK24: 0 | AL24: IT | AM24: +39 334 830 1760 | AN24: difrancomirco1992@gmail.com; | AO24: -
A25: 99000551 | B25: BAR TABACCHI DI TARANTINI ANTONIO | C25: 00984250159 | D25: TRNNTN41H30L328F | E25: VIA DEI CINQUECENTO 22 - 20139 MILANO MI | F25: Y | H25: ITE48D0900S0001 | I25: TARANTINI ANTONIO | J25: 00984250159 | K25: 821566 | L25: MI | M25: TRNNTN41H30L328F | N25: VIA DEI CINQUECENTO 0025 | O25: 20139 | P25: MILANO | R25: MI | S25: LOMBARDIA | T25: Attiva | U25: IMPRESA INDIVIDUALE | V25: IMPRESE INDIVIDUALI | X25: TARANTINI | Y25: ANTONIO | Z25: M | AA25: 30/06/1941 | AB25: BT | AC25: TRANI | AD25: IT | AE25: 0 | AF25: VIA DEI CINQUECENTO 0025 | AG25: 20139 | AH25: MILANO | AI25: MI | AJ25: 0 | AK25: 0 | AL25: IT | AM25: 0255212400 - 3477788766 | AN25: domenicotarantina@tiscali.it; domenicotarantini@tiscali.it | AO25: -
A26: 99000577 | B26: DELLE VERGINI BERNARDO | C26: 01026680718 | D26: DLLBNR61H19I072G | E26: VIA XX SETTEMBRE 7 - 71010 SAN PAOLO DI CIVITATE FG | F26: Y | H26: ITA98C0A02S0001 | I26: DELLE VERGINI BERNARDO | J26: 01026680718 | K26: 128770 | L26: FG | M26: DLLBNR61H19I072G | N26: VIA XX SETTEMBRE 7/9 | O26: 71010 | P26: SAN PAOLO DI CIVITATE | R26: FG | S26: PUGLIA | T26: Attiva | U26: IMPRESA INDIVIDUALE | V26: IMPRESE INDIVIDUALI | X26: DELLE VERGINI | Y26: BERNARDO NATALE | Z26: M | AA26: 19/06/1961 | AB26: FG | AC26: SAN PAOLO DI CIVITATE | AD26: IT | AE26: 0 | AF26: VIA LEOPARDI | AG26: 71010 | AH26: SAN PAOLO DI CIVITATE | AI26: FG | AJ26: 0 | AK26: 0 | AL26: 0 | AM26: 0882552364 - 3479379290 | AN26: barbernardo@libero.it; | AO26: -
A27: 99009296 | B27: ARTE TIPOGRAFICA DI ZAGARESE ANGELO | C27: 01055660623 | D27: ZGRNGL67S27A783F | E27: VIA P. COLUMBRO ZONA S.COLOMBA - 82100 BENEVENTO BN | F27: Y | H27: ITEF810006S0001 | I27: ARTE TIPOGRAFICA DI ZAGARESE ANGELO | J27: 01055660623 | K27: 77480 | L27: BN | M27: ZGRNGL67S27A783F | N27: VIA P. COLUMBRO ZONA S.COLOMBA | O27: 82100 | P27: BENEVENTO | R27: BN | S27: CAMPANIA | T27: Attiva | U27: IMPRESA INDIVIDUALE | V27: IMPRESE INDIVIDUALI | X27: ZAGARESE | Y27: ANGELO | Z27: M | AA27: 27/11/1967 | AB27: BN | AC27: BENEVENTO | AD27: IT | AE27: 0 | AF27: VIA DUCA D' AOSTA 6 | AG27: 82100 | AH27: BENEVENTO | AI27: BN | AJ27: 0 | AK27: 0 | AL27: 0 | AM27: 0824363392 - 3280237216 | AN27: tabax@libero.it; | AO27: -
A28: 99013491 | B28: VERDE MARIA ROSARIA | C28: 01067450617 | D28: VRDMRS60E54C561B | E28: VIA UMBERTO I 56, 81030, CESA (CE) | F28: Y | H28: ITF3A7010BS0001 | J28: 01067450617 | K28: 99680 | L28: CE | M28: VRDMRS60E54C561B | T28: Cessata favorevole | U28: IMPRESA INDIVIDUALE | V28: IMPRESE INDIVIDUALI | X28: - | Y28: - | Z28: - | AA28: - | AB28: - | AC28: - | AD28: - | AE28: - | AF28: - | AG28: - | AH28: - | AI28: - | AJ28: - | AK28: - | AL28: - | AM28: 0815021650 - 3891225553 | AN28: giulio.parisini@hotmail.it; | AO28: -
A29: 99013460 | B29: GUIDI ELENA | C29: 01097530503 | D29: GDULNE61E69G702T | E29: VIA NAZARIO SAURO 183, 56021, CASCINA (PI) | F29: Y | H29: IT8F820601S0001 | I29: GUIDI ELENA | J29: 01097530503 | K29: 100919 | L29: PI | M29: GDULNE61E69G702T | N29: VIA NAZARIO SAURO 183 | O29: 56021 | P29: CASCINA | Q29: LATIGNANO | R29: PI | S29: TOSCANA | T29: Attiva | U29: IMPRESA INDIVIDUALE | V29: IMPRESE INDIVIDUALI | X29: GUIDI | Y29: ELENA | Z29: F | AA29: 29/05/1961 | AB29: PI | AC29: PISA | AD29: IT | AE29: 0 | AF29: VIA ROTINA 163 | AG29: 56021 | AH29: CASCINA | AI29: PI | AJ29: LATIGNANO | AK29: 0 | AL29: 0 | AM29: 050780452 - 3470363324 | AN29: francescomartinelli88@gmail.com; | AO29: -
A30: 99014789 | B30: BAR TABACCHI DA ANTONIETTA DI FILIPPONI MATTEO | C30: 01147060576 | D30: FLPMTT88L13H282G | E30: PONTE CRISPOLTI - 02010 RIVODUTRI | F30: Y | H30: ITA71C030BS0001 | I30: BAR TABACCHI DA ANTONIETTA DI FILIPPONI MATTEO | J30: 01147060576 | K30: 71689 | L30: RI | M30: FLPMTT88L13H282G | N30: LOCALITA' PONTE CRISPOLTI 6 | O30: 02010 | P30: RIVODUTRI | R30: RI | S30: LAZIO | T30: Attiva | U30: IMPRESA INDIVIDUALE | V30: IMPRESE INDIVIDUALI | X30: FILIPPONI | Y30: MATTEO | Z30: M | AA30: 13/07/1988 | AB30: RI | AC30: RIETI | AD30: IT | AE30: 0 | AF30: LOCALITA' PONTE CRISPOLTI 7 | AG30: 02010 | AH30: RIVODUTRI | AI30: RI | AJ30: 0 | AK30: 0 | AL30: IT | AM30: 328-5463547 | AN30: MATTOFILLO@GMAIL.COM; | AO30: -
A31: 99008509 | B31: BAR GELATERIA CREPERIA CAPRICE 2 DI BERNACCA MATTEO & C. SNC | C31: 01164970459 | D31: 01164970459 | E31: VIA CARDUCCI GIOSUE' 3, 54033, CARRARA (MS) | F31: Y | H31: IT8068080DS0001 | I31: BAR GELATERIA CREPERIA CAPRICE 2 DI BERNACCA MATTEO & C. SNC | J31: 01164970459 | K31: 118323 | L31: MS | M31: 01164970459 | N31: VIA CARDUCCI GIOSUE' 3 | O31: 54033 | P31: CARRARA | R31: MS | S31: TOSCANA | T31: Attiva | U31: SOCIETA' IN NOME COLLETTIVO | V31: SOCIETA' DI PERSONE | X31: MURACCHIOLI | Y31: ARIANNA | Z31: F | AA31: 08/07/1982 | AB31: MS | AC31: MASSA | AD31: IT | AE31: 0 | AF31: VIA CASTAGNOLA DI SOTTO 65 | AG31: 54100 | AH31: MASSA | AI31: MS | AJ31: 0 | AK31: 0 | AL31: IT | AM31: 0585846163 - 3476100512 | AN31: aryanna221@yahoo.it; | AO31: -
A32: 99013180 | B32: LUIGI E DAIGORO S.R.L.S. | C32: 01170840571 | D32: 01170840571 | E32: VIA SANDRO PERTINI 211 - 02100 RIETI | F32: Y | H32: IT9E950A0BS0001 | I32: LUIGI E DAIGORO S.R.L.S. | J32: 01170840571 | K32: 73387 | L32: RI | M32: 01170840571 | N32: VIA SANDRO PERTINI 211 | O32: 02100 | P32: RIETI | R32: RI | S32: LAZIO | T32: Attiva | U32: SOCIETA' A RESPONSABILITA' LIMITATA SEMPLIFICATA | V32: SOCIETA' DI CAPITALE | X32: CELLI | Y32: MARIA LUIGIA | Z32: F | AA32: 20/06/1958 | AB32: RI | AC32: RIETI | AD32: 0 | AE32: 0 | AF32: VIA SALARIA PER L'AQUILA 41 | AG32: 02100 | AH32: RIETI | AI32: RI | AJ32: 0 | AK32: 0 | AL32: IT | AM32: 3917154863 - 3927121987 | AN32: luigiedaigorosrls@gmail.com; | AO32: -
A33: 99013472 | B33: IL TABACCHINO DI EMANUELA DAL FERRO | C33: 01186460950 | D33: DLFMNL76L45E591O | E33: CORSO CATTEDRALE 56, 09091, ALES (OR) | F33: Y | H33: IT8A1D080CS0001 | I33: IL TABACCHINO DI EMANUELA DAL FERRO | J33: 01186460950 | K33: 137269 | L33: OR | M33: DLFMNL76L45E591O | N33: CORSO CATTEDRALE 56 | O33: 09091 | P33: ALES | R33: OR | S33: SARDEGNA | T33: Attiva | U33: IMPRESA INDIVIDUALE | V33: IMPRESE INDIVIDUALI | X33: DAL FERRO | Y33: EMANUELA | Z33: F | AA33: 05/07/1976 | AB33: MI | AC33: LIMBIATE | AD33: IT | AE33: 0 | AF33: VIA IV NOVEMBRE 48 | AG33: 09091 | AH33: ALES | AI33: OR | AJ33: 0 | AK33: 0 | AL33: IT | AM33: 0783998852 - 3452448186 | AN33: iltabacchinoales@gmail.com; | AO33: -
A34: 99006385 | B34: CAFFE' LIDIA SNCDEI FRATELLI CERBINO | C34: 01192620761 | D34: 01192620761 | E34: PIAZZA VITTORIO EMANUELE 12 - 85048 ROTONDA PZ | F34: Y | H34: IT560D0C0DS0001 | I34: CAFFE' LIDIA SNC DEI FRATELLI CERBINO | J34: 01192620761 | K34: 83902 | L34: PZ | M34: 01192620761 | N34: PIAZZA VITTORIO EMANUELE 12 | O34: 85048 | P34: ROTONDA | R34: PZ | S34: BASILICATA | T34: Attiva | U34: SOCIETA' IN NOME COLLETTIVO | V34: SOCIETA' DI PERSONE | X34: CERBINO | Y34: FRANCESCO | Z34: M | AA34: 20/05/1960 | AB34: PZ | AC34: ROTONDA | AD34: IT | AE34: 0 | AF34: VIA ALDO MORO 3 | AG34: 85048 | AH34: ROTONDA | AI34: PZ | AJ34: 0 | AK34: 0 | AL34: 0 | AM34: 0973661171 | AN34: antoniocerbino9@gmail.com; antoniocervino9@gmail.com | AO34: -
A35: 99000737 | B35: D'ANGELO ROBERTO | C35: 01198750448 | D35: DNGRRT65S19H769C | E35: VIA GALILEO GALILEI 1 - 63066 GROTTAMMARE AP | F35: Y | H35: IT9F8B0A0BS0001 | I35: D'ANGELO ROBERTO | J35: 01198750448 | K35: 120626 | L35: AP | M35: DNGRRT65S19H769C | N35: VIA GALILEO GALILEI 1 | O35: 63066 | P35: GROTTAMMARE | R35: AP | S35: MARCHE | T35: Attiva | U35: IMPRESA INDIVIDUALE | V35: IMPRESE INDIVIDUALI | X35: D'ANGELO | Y35: ROBERTO | Z35: M | AA35: 19/11/1965 | AB35: AP | AC35: SAN BENEDETTO DEL TRONTO | AD35: IT | AE35: 0 | AF35: VIA GIAN LORENZO BERNINI 86 | AG35: 63066 | AH35: GROTTAMMARE | AI35: AP | AJ35: 0 | AK35: 0 | AL35: IT | AM35: 0735736064 | AN35: taroda65@gmail.com; | AO35: -
A36: 99000740 | B36: BAR COMMERCIO DI ROGNONI R. | C36: 01203900186 | D36: RGNRRT67R30G388W | E36: PIAZZA BONACCOSA 10 - 27020 DORNO PV | F36: Y | H36: IT564B040ES0001 | I36: ROGNONI ROBERTO | J36: 01203900186 | K36: 172994 | L36: PV | M36: RGNRRT67R30G388W | N36: PIAZZA BONACOSSA 10 | O36: 27020 | P36: DORNO | R36: PV | S36: LOMBARDIA | T36: Attiva | U36: IMPRESA INDIVIDUALE | V36: IMPRESE INDIVIDUALI | X36: ROGNONI | Y36: ROBERTO | Z36: M | AA36: 30/10/1967 | AB36: PV | AC36: PAVIA | AD36: IT | AE36: 0 | AF36: 0 | AG36: 0 | AH36: 0 | AI36: 0 | AJ36: 0 | AK36: 0 | AL36: 0 | AM36: 038284028 | AN36: simobibo@libero.it; | AO36: -
A37: 99009572 | B37: CANTONI DA.RO. SRL | C37: 01211820160 | D37: 01211820160 | E37: VIA I MAGGIO 2/4 - 24060 GORLAGO BG | F37: Y | H37: ITF2840402S0001 | I37: CANTONI DA.RO. SRL | J37: 01211820160 | K37: 193775 | L37: BG | M37: 01211820160 | N37: VIA I MAGGIO 2/4 | O37: 24060 | P37: GORLAGO | R37: BG | S37: LOMBARDIA | T37: Attiva | U37: SOCIETA' A RESPONSABILITA' LIMITATA | V37: SOCIETA' DI CAPITALE | X37: CANTONI | Y37: ROBERTO | Z37: M | AA37: 23/01/1972 | AB37: BG | AC37: TRESCORE BALNEARIO | AD37: IT | AE37: 0 | AF37: VIA GUGLIELMO MARCONI 34 | AG37: 24060 | AH37: CAROBBIO DEGLI ANGELI | AI37: BG | AJ37: 0 | AK37: 0 | AL37: IT | AM37: 035951037 - 3456987138 | AN37: roberto_cantoni@virgilio.it; roberto@bowlinggorlago.com | AO37: -
A38: 99004361 | B38: TABACCHERIA RIV. N. 3DI MOSCA NADIA | C38: 01212310088 | D38: MSCNDA64H62F704J | E38: VIA ROMA 3 - 18012 BORDIGHERA IM | F38: Y | H38: IT990B060DS0001 | I38: MOSCA NADIA | J38: 01212310088 | K38: 107871 | L38: IM | M38: MSCNDA64H62F704J | N38: VIA ROMA 3 | O38: 18012 | P38: BORDIGHERA | R38: IM | S38: LIGURIA | T38: Attiva | U38: IMPRESA INDIVIDUALE | V38: IMPRESE INDIVIDUALI | X38: MOSCA | Y38: NADIA | Z38: F | AA38: 22/06/1964 | AB38: MB | AC38: MONZA | AD38: IT | AE38: 0 | AF38: VIA CESARE BALBO 1 | AG38: 18012 | AH38: BORDIGHERA | AI38: IM | AJ38: 0 | AK38: 0 | AL38: 0 | AM38: 0184260783 - 3926967366 | AN38: tnsf@libero.it; | AO38: -
A39: 99008458 | B39: BAR MADISON DI GUASCONI FEDERICA | C39: 01226030334 | D39: GSCFRC65R63G535Z | E39: VIA EMANUELLI ANGOLO VIA PUCCINI 54 - 29121 PIACENZA PC | F39: Y | H39: ITAD89090ES0001 | I39: BAR MADISON DI GUASCONI FEDERICA | J39: 01226030334 | K39: 144086 | L39: PC | M39: GSCFRC65R63G535Z | N39: VIA EMANUELLI ANGOLO VIA PUCCINI 54 | O39: 29100 | P39: PIACENZA | R39: PC | S39: EMILIA-ROMAGNA | T39: Attiva | U39: IMPRESA INDIVIDUALE | V39: IMPRESE INDIVIDUALI | X39: GUASCONI | Y39: FEDERICA | Z39: F | AA39: 23/10/1965 | AB39: PC | AC39: PIACENZA | AD39: IT | AE39: 0 | AF39: VIA AMILCARE PONCHIELLI 15 | AG39: 29121 | AH39: PIACENZA | AI39: PC | AJ39: 0 | AK39: 0 | AL39: 0 | AM39: 366 6614314 | AN39: bar.madison@libero.it; | AO39: -
A40: 99000777 | B40: TREOSSI FRANCESCA | C40: 01235690391 | D40: TRSFNC72C41H199F | E40: VIA DISMANO 621 - 48100 RAVENNA RA | F40: Y | H40: IT4E490E0ES0001 | I40: TREOSSI FRANCESCA | J40: 01235690391 | K40: 172479 | L40: RA | M40: TRSFNC72C41H199F | N40: VIA DISMANO 621 | O40: 48125 | P40: RAVENNA | Q40: SAN ZACCARIA | R40: RA | S40: EMILIA-ROMAGNA | T40: Attiva | U40: IMPRESA INDIVIDUALE | V40: IMPRESE INDIVIDUALI | X40: TREOSSI | Y40: FRANCESCA | Z40: F | AA40: 01/03/1972 | AB40: RA | AC40: RAVENNA | AD40: IT | AE40: 0 | AF40: VIA MALVA NORD 61 | AG40: 48015 | AH40: CERVIA | AI40: RA | AJ40: 0 | AK40: 0 | AL40: IT | AM40: 0544564856 - 3356040141 | AN40: caffetteria2005@hotmail.it; | AO40: -
A41: 99004792 | B41: DE BONIS PASQUALE | C41: 01298210764 | D41: DBNPQL69L04G942D | E41: VIALE DEL BASENTO 46 - 85100 POTENZA PZ | F41: Y | H41: IT996F0509S0001 | I41: DE BONIS PASQUALE | J41: 01298210764 | K41: 104397 | L41: PZ | M41: DBNPQL69L04G942D | N41: VIALE DEL BASENTO 46 | O41: 85100 | P41: POTENZA | R41: PZ | S41: BASILICATA | T41: Attiva | U41: IMPRESA INDIVIDUALE | V41: IMPRESE INDIVIDUALI | X41: DE BONIS | Y41: PASQUALE | Z41: M | AA41: 04/07/1969 | AB41: PZ | AC41: POTENZA | AD41: IT | AE41: 0 | AF41: CNT SERRA 80 | AG41: 85050 | AH41: TITO | AI41: PZ | AJ41: 0 | AK41: 0 | AL41: 0 | AM41: 097158568 - 3391260314 | AN41: pasqualedebonis@libero.it; | AO41: -
A42: 99009616 | B42: QUEEN GAMES DI VORIA GILL | C42: 01321160523 | D42: VROGLL74L18A091K | E42: VIALE PIETRO TOSELLI 94 - 53100 SIENA | F42: Y | H42: IT98E6070CS0001 | I42: QUEEN GAMES DI VORIA GILL | J42: 01321160523 | K42: 138448 | L42: SI | M42: VROGLL74L18A091K | N42: VIALE PIETRO TOSELLI 94 | O42: 53100 | P42: SIENA | R42: SI | S42: TOSCANA | T42: Attiva | U42: IMPRESA INDIVIDUALE | V42: IMPRESE INDIVIDUALI | X42: VORIA | Y42: GILL | Z42: M | AA42: 18/07/1974 | AB42: SA | AC42: AGROPOLI | AD42: IT | AE42: 0 | AF42: VIA DARIO NERI 53 | AG42: 53100 | AH42: SIENA | AI42: SI | AJ42: 0 | AK42: 0 | AL42: 0 | AM42: 0577223873 - 339 6328475 | AN42: bene02@libero.it; | AO42: -
A43: 99015417 | B43: BAR FIORI DI BERNASCONI ANDREA E C. S.A.S. | C43: 01328600190 | D43: 01328600190 | E43: VIA TENSINI, 36, 26013 CREMA (CR), | F43: Y | H43: IT4D850C05S0001 | I43: BAR FIORI DI BERNASCONI ANDREA E C. SAS | J43: 01328600190 | K43: 161941 | L43: CR | M43: 01328600190 | N43: VIA TENSINI 36 | O43: 26013 | P43: CREMA | R43: CR | S43: LOMBARDIA | T43: Attiva | U43: SOCIETA' IN ACCOMANDITA SEMPLICE | V43: SOCIETA' DI PERSONE | X43: BERNASCONI | Y43: ANDREA | Z43: M | AA43: 04/04/1978 | AB43: LO | AC43: LODI | AD43: IT | AE43: 0 | AF43: 0 | AG43: 0 | AH43: 0 | AI43: 0 | AJ43: 0 | AK43: 0 | AL43: 0 | AM43: - | AN43: - | AO43: -
A44: 99014536 | B44: GREEN PARK SOC A RESPONSABILITA LIMITATA SEMPLIFICATA | C44: 01337800773 | D44: 01337800773 | E44: ORAZIO FLACCO - 75012 BERNALDA | F44: Y | H44: ITA5900E0CS0001 | I44: GREEN PARK SRL SEMPLIFICATA | J44: 01337800773 | K44: 91454 | L44: MT | M44: 01337800773 | N44: VIALE ORAZIO FLACCO 14 | O44: 75012 | P44: BERNALDA | Q44: METAPONTO | R44: MT | S44: BASILICATA | T44: Attiva | U44: SOCIETA' A RESPONSABILITA' LIMITATA SEMPLIFICATA | V44: SOCIETA' DI CAPITALE | X44: FUINA | Y44: GIANFRANCO | Z44: M | AA44: 04/10/1983 | AB44: MT | AC44: PISTICCI | AD44: 0 | AE44: 0 | AF44: PIAZZA LOMBARDO RADICE 11/B | AG44: 75012 | AH44: BERNALDA | AI44: MT | AJ44: 0 | AK44: 0 | AL44: IT | AM44: 3454277253 | AN44: greenparkbarmetaponto@gmail.com; | AO44: -
A45: 99012499 | B45: TODISCO ELENA | C45: 01339460766 | D45: TDSLNE65B62F839N | E45: LARGO VITTORIO VENETO 35 - 85057 TRAMUTOLA PZ | F45: Y | H45: ITB7050C0AS0001 | I45: TODISCO ELENA | J45: 01339460766 | K45: 134428 | L45: PZ | M45: TDSLNE65B62F839N | N45: LARGO VITTORIO VENETO 35 | O45: 85057 | P45: TRAMUTOLA | R45: PZ | S45: BASILICATA | T45: Attiva | U45: IMPRESA INDIVIDUALE | V45: IMPRESE INDIVIDUALI | X45: TODISCO | Y45: ELENA | Z45: F | AA45: 22/02/1965 | AB45: NA | AC45: NAPOLI | AD45: IT | AE45: 0 | AF45: LARGO VITTORIO VENETO 35 | AG45: 85057 | AH45: TRAMUTOLA | AI45: PZ | AJ45: 0 | AK45: 0 | AL45: 0 | AM45: 329-3725456 | AN45: arge86@hotmail.it; | AO45: -
A46: 99013136 | B46: FASANO EUSTACHIO | C46: 01341540779 | D46: FSNSCH92T07F052V | E46: VICO PRIMO LAMARTELLA, 19/21/23 - 75100 MATERA MT | F46: Y | H46: ITAD900705S0001 | J46: 01341540779 | K46: 91751 | L46: MT | M46: FSNSCH92T07F052V | T46: Cessata favorevole | U46: IMPRESA INDIVIDUALE | V46: IMPRESE INDIVIDUALI | X46: - | Y46: - | Z46: - | AA46: - | AB46: - | AC46: - | AD46: - | AE46: - | AF46: - | AG46: - | AH46: - | AI46: - | AJ46: - | AK46: - | AL46: - | AM46: 3425201533 | AN46: fasano.uccio@hotmail.it; | AO46: -
A47: 99000945 | B47: CIANI SILVIA | C47: 01363660414 | D47: CNISLV70H67G479Y | E47: VIA ZAMBONINI, 13 - 61025 MONTELABBATE PU | F47: Y | H47: IT67AE080FS0001 | I47: CENTRO SETTE DI CIANI SILVIA | J47: 01363660414 | K47: 126531 | L47: PS | M47: CNISLV70H67G479Y | N47: VIA ZAMBONINI 13/15 | O47: 61025 | P47: MONTELABBATE | R47: PU | S47: MARCHE | T47: Attiva | U47: IMPRESA INDIVIDUALE | V47: IMPRESE INDIVIDUALI | X47: CIANI | Y47: SILVIA | Z47: F | AA47: 27/06/1970 | AB47: PU | AC47: PESARO | AD47: IT | AE47: 0 | AF47: VIA DELLE REGIONI 10 | AG47: 61022 | AH47: VALLEFOGLIA | AI47: PU | AJ47: 0 | AK47: 0 | AL47: IT | AM47: 0721491135 | AN47: centrosette@alice.it; | AO47: -
A48: 99014986 | B48: BAR LE FONTI DI SESTINI MASSIMO & C. S.N.C. | C48: 01368950513 | D48: 01368950513 | E48: FIORENTINA - 52048 MONTE SAN SAVINO | F48: Y | H48: IT762A0F08S0001 | I48: BAR LE FONTI DI SESTINI MASSIMO & C. SNC | J48: 01368950513 | K48: 101137 | L48: AR | M48: 01368950513 | N48: VIA FIORENTINA 3 | O48: 52048 | P48: MONTE SAN SAVINO | R48: AR | S48: TOSCANA | T48: Attiva | U48: SOCIETA' IN NOME COLLETTIVO | V48: SOCIETA' DI PERSONE | X48: SESTINI | Y48: MASSIMO | Z48: M | AA48: 21/06/1968 | AB48: AR | AC48: MONTE SAN SAVINO | AD48: IT | AE48: 0 | AF48: VIA BUGIANA 66 | AG48: 52048 | AH48: MONTE SAN SAVINO | AI48: AR | AJ48: 0 | AK48: 0 | AL48: 0 | AM48: 0575 810654 - 3333875018 MA... | AN48: MASSIMO@GSBARLEFONTI.IT; | AO48: -
A49: 99015612 | B49: COLFAB SNC DI COLUCCI GIANVITO & FABIANO VINCENZO | C49: 01397560770 | D49: 01397560770 | E49: I LA MARTELLA - 75100 MATERA | F49: Y | H49: ITA3D50201S0001 | I49: COLFAB SNC DI COLUCCI GIANVITO & FABIANO VINCENZO | J49: 01397560770 | K49: 210465 | L49: MT | M49: 01397560770 | N49: VICO I LA MARTELLA 21-23 | O49: 75100 | P49: MATERA | R49: MT | S49: BASILICATA | T49: Attiva | U49: SOCIETA' IN NOME COLLETTIVO | V49: SOCIETA' DI PERSONE | X49: COLUCCI | Y49: GIANVITO | Z49: M | AA49: 29/05/1989 | AB49: MT | AC49: MATERA | AD49: 0 | AE49: 0 | AF49: VIA DON LUIGI STURZO 15 | AG49: 75100 | AH49: MATERA | AI49: MT | AJ49: 0 | AK49: 0 | AL49: IT | AM49: 3294341145 | AN49: gianvito.colucci@hotmail.it; | AO49: -
A50: 99004617 | B50: PARISI FRANCESCO | C50: 01404160622 | D50: PRSFNC81L11A783M | E50: VIA VACCARIELLO 7 - 83017 ROTONDI AV | F50: Y | H50: ITC30D0C04S0001 | I50: PARISI FRANCESCO | J50: 01404160622 | K50: 164118 | L50: AV | M50: PRSFNC81L11A783M | N50: VIA VACCARIELLO L. 7 | O50: 83017 | P50: ROTONDI | R50: AV | S50: CAMPANIA | T50: Attiva | U50: IMPRESA INDIVIDUALE | V50: IMPRESE INDIVIDUALI | X50: PARISI | Y50: FRANCESCO | Z50: M | AA50: 11/07/1981 | AB50: BN | AC50: BENEVENTO | AD50: IT | AE50: 0 | AF50: VIA APPIA EST 13 | AG50: 82011 | AH50: ARPAIA | AI50: BN | AJ50: 0 | AK50: 0 | AL50: 0 | AM50: 0824843789 - 3200440025 | AN50: giocatel@libero.it; | AO50: -
A51: 99013880 | B51: BETTING G SRLS | C51: 01414450450 | D51: 01414450450 | E51: LUNENSE - 54033 CARRARA | F51: Y | H51: ITDE5D0B0ES0001 | I51: BETTING G SRL SEMPLIFICATA | J51: 01414450450 | K51: 139143 | L51: MS | M51: 01414450450 | N51: VIA LUNENSE 35/C | O51: 54033 | P51: CARRARA | R51: MS | S51: TOSCANA | T51: Attiva | U51: SOCIETA' A RESPONSABILITA' LIMITATA SEMPLIFICATA | V51: SOCIETA' DI CAPITALE | X51: FRANCESCHI | Y51: LUCA | Z51: M | AA51: 10/10/1974 | AB51: MS | AC51: CARRARA | AD51: 0 | AE51: 0 | AF51: VIA PALVOTRISIA 68 | AG51: 19033 | AH51: CASTELNUOVO MAGRA | AI51: SP | AJ51: 0 | AK51: 0 | AL51: IT | AM51: 3206620747 | AN51: gabrigenti@hotmail.it; | AO51: -
A52: 99001091 | B52: BAR CENTRALE DI MASTROSIMONE MICHELE | C52: 01464530763 | D52: MSTMHL71H06I305M | E52: CORSO VITTORIO EMANUELE 7 | F52: Y | H52: IT8A020506S0001 | I52: BAR CENTRALE DI MASTROSIMONE MICHELE | J52: 01464530763 | K52: 111605 | L52: PZ | M52: MSTMHL71H06I305M | N52: CORSO VITTORIO EMANUELE 7 | O52: 85037 | P52: SANT'ARCANGELO | R52: PZ | S52: BASILICATA | T52: Attiva | U52: IMPRESA INDIVIDUALE | V52: IMPRESE INDIVIDUALI | X52: MASTROSIMONE | Y52: MICHELE | Z52: M | AA52: 06/06/1971 | AB52: PZ | AC52: SANT'ARCANGELO | AD52: IT | AE52: 0 | AF52: CORSO VITTORIO EMANUELE 7 | AG52: 85037 | AH52: SANT'ARCANGELO | AI52: PZ | AJ52: 0 | AK52: 0 | AL52: 0 | AM52: 0973619140 | AN52: mastro89@barmastrosimonine.191.it; barcentrale1971@gmail.com | AO52: -
A53: 99009306 | B53: LOPEZ GERARDO | C53: 01521580785 | D53: LPZGRD64R22H919N | E53: VIA ROMA 157 - 87055 SAN GIOVANNI IN FIORE CS | F53: Y | H53: IT558E0D08S0001 | I53: LOPEZ GERARDO | J53: 01521580785 | K53: 107360 | L53: CS | M53: LPZGRD64R22H919N | N53: VIA ROMA 157 | O53: 87055 | P53: SAN GIOVANNI IN FIORE | R53: CS | S53: CALABRIA | T53: Attiva | U53: IMPRESA INDIVIDUALE | V53: IMPRESE INDIVIDUALI | X53: LOPEZ | Y53: GERARDO | Z53: M | AA53: 22/10/1964 | AB53: CS | AC53: SAN GIOVANNI IN FIORE | AD53: IT | AE53: 0 | AF53: VIA ALFIERI 48 | AG53: 87055 | AH53: SAN GIOVANNI IN FIORE | AI53: CS | AJ53: 0 | AK53: 0 | AL53: 0 | AM53: 0984-992709 - 3899359088 | AN53: gerryarnolds1987@libero.it; | AO53: -
A54: 99015141 | B54: GIOCOVENTUNO SAS DI VANESSA BACCHINUCCI & C. | C54: 01524920111 | D54: 01524920111 | E54: SARZANA - 19136 LA SPEZIA | F54: Y | H54: ITECDF0402S0001 | I54: GIOCOVENTUNO SAS DI VANESSA BACCHINUCCI & C. | J54: 01524920111 | K54: 225803 | L54: SP | M54: 01524920111 | N54: VIA SARZANA 977/979 | O54: 19136 | P54: LA SPEZIA | R54: SP | S54: LIGURIA | T54: Attiva | U54: SOCIETA' IN ACCOMANDITA SEMPLICE | V54: SOCIETA' DI PERSONE | X54: BACCHINUCCI | Y54: VANESSA | Z54: F | AA54: 23/11/1987 | AB54: SP | AC54: SARZANA | AD54: 0 | AE54: 0 | AF54: VIA DELLA REPUBBLICA 87 | AG54: 19032 | AH54: LERICI | AI54: SP | AJ54: 0 | AK54: 0 | AL54: IT | AM54: 3203503355 | AN54: giacopinellimassimo@libero.it; | AO54: -
A55: 99008858 | B55: FUSCO FABIO | C55: 01534860596 | D55: FSCFBA64P12H501L | E55: VIA NETTUNENSE KM 22.820 - 04011 APRILIA LT | F55: Y | H55: IT59080E0DS0001 | I55: FUSCO FABIO | J55: 01534860596 | K55: 95758 | L55: LT | M55: FSCFBA64P12H501L | N55: VIA NETTUNENSE KM 22 820 | O55: 04011 | P55: APRILIA | R55: LT | S55: LAZIO | T55: Attiva | U55: IMPRESA INDIVIDUALE | V55: IMPRESE INDIVIDUALI | X55: FUSCO | Y55: FABIO | Z55: M | AA55: 12/09/1964 | AB55: RM | AC55: ROMA | AD55: IT | AE55: 0 | AF55: VIA DUCA DEGLI ABRUZZI 23 | AG55: 67030 | AH55: ALFEDENA | AI55: AQ | AJ55: 0 | AK55: 0 | AL55: IT | AM55: 069282579 - 3389538961 CA | AN55: fabiofusco024@inwind.it; | AO55: -
A56: 99013879 | B56: SAILER JOSEF | C56: 01536450214 | D56: SLRJSF41M04Z102U | E56: HAUPTSTRASSE - 39028 SILANDRO | F56: Y | H56: ITC3A5090AS0001 | I56: SAILER JOSEF | J56: 01536450214 | K56: 197307 | L56: BZ | M56: SLRJSF41M04Z102U | N56: VIA PRINCIPALE 48 | O56: 39028 | P56: SILANDRO | R56: BZ | S56: TRENTINO-ALTO ADIGE | T56: Attiva | U56: IMPRESA INDIVIDUALE | V56: IMPRESE INDIVIDUALI | X56: SAILER | Y56: JOSEF | Z56: M | AA56: 04/08/1941 | AB56: 0 | AC56: JENBACH | AD56: AT | AE56: 0 | AF56: VIA PRINCIPALE 50 | AG56: 39028 | AH56: SILANDRO | AI56: BZ | AJ56: 0 | AK56: 0 | AL56: 0 | AM56: 3319818773 MA | AN56: info@barcremona.com; | AO56: -
A57: 99013211 | B57: TIKI TAKA SRLS | C57: 01562180883 | D57: 01562180883 | E57: DALIA - 97018 SCICLI | F57: Y | H57: ITC81A0D0AS0001 | I57: TIKI TAKA SRL SEMPLIFICATA | J57: 01562180883 | K57: 129542 | L57: RG | M57: 01562180883 | N57: VIA DALIA 29 | O57: 97018 | P57: SCICLI | R57: RG | S57: SICILIA | T57: Attiva | U57: SOCIETA' A RESPONSABILITA' LIMITATA SEMPLIFICATA | V57: SOCIETA' DI CAPITALE | X57: OCCHIPINTI | Y57: DAMIANO | Z57: M | AA57: 03/08/1989 | AB57: RG | AC57: SCICLI | AD57: 0 | AE57: 0 | AF57: VIA XXV APRILE 14 | AG57: 97018 | AH57: SCICLI | AI57: RG | AJ57: 0 | AK57: 0 | AL57: IT | AM57: 392-7070438 | AN57: luigiimplatini@gmail.com; | AO57: -
A58: 99009733 | B58: BAZZANO ALFREDO | C58: 01569580093 | D58: BZZLRD68A06E632G | E58: VIA AURELIA 224 - 17025 LOANO | F58: Y | H58: ITF54A050DS0001 | I58: BAZZANO ALFREDO | J58: 01569580093 | K58: 157883 | L58: SV | M58: BZZLRD68A06E632G | N58: VIA AURELIA 224 | O58: 17025 | P58: LOANO | R58: SV | S58: LIGURIA | T58: Attiva | U58: IMPRESA INDIVIDUALE | V58: IMPRESE INDIVIDUALI | X58: BAZZANO | Y58: ALFREDO | Z58: M | AA58: 06/01/1968 | AB58: SV | AC58: LOANO | AD58: IT | AE58: 0 | AF58: VIA SAN DAMIANO 17 | AG58: 17025 | AH58: LOANO | AI58: SV | AJ58: 0 | AK58: 0 | AL58: 0 | AM58: 19666039 - 3389617148 | AN58: alfredo.bazzano@yahoo.it; | AO58: -
A59: 99014539 | B59: CARZEDDA STEFANO | C59: 01572450912 | D59: CRZSFN81M13F979H | E59: ROMA - 08029 SINISCOLA | F59: Y | H59: IT4A540F02S0001 | I59: CARZEDDA STEFANO | J59: 01572450912 | K59: 112214 | L59: NU | M59: CRZSFN81M13F979H | N59: VIA ROMA 99 | O59: 08029 | P59: SINISCOLA | R59: NU | S59: SARDEGNA | T59: Attiva | U59: IMPRESA INDIVIDUALE | V59: IMPRESE INDIVIDUALI | X59: CARZEDDA | Y59: STEFANO | Z59: M | AA59: 13/08/1981 | AB59: NU | AC59: NUORO | AD59: IT | AE59: 0 | AF59: VIA ANGIOI 23 | AG59: 08029 | AH59: SINISCOLA | AI59: NU | AJ59: 0 | AK59: 0 | AL59: 0 | AM59: 3801787836 | AN59: stecarzedda@outlook.com; | AO59: -
A60: 99012026 | B60: MURRI MICHELE | C60: 01573420534 | D60: MRRMHL84A06G088A | E60: PIAZZA ZUCCHI 4, 58011, CAPALBIO (GR) | F60: Y | H60: ITE9170305S0001 | I60: MURRI MICHELE | J60: 01573420534 | K60: 136385 | L60: GR | M60: MRRMHL84A06G088A | N60: PIAZZA ZUCCHI 4 | O60: 58011 | P60: CAPALBIO | R60: GR | S60: TOSCANA | T60: Attiva | U60: IMPRESA INDIVIDUALE | V60: IMPRESE INDIVIDUALI | X60: MURRI | Y60: MICHELE | Z60: M | AA60: 06/01/1984 | AB60: GR | AC60: ORBETELLO | AD60: IT | AE60: 0 | AF60: PIAZZALE CORALLO 21 | AG60: 58011 | AH60: CAPALBIO | AI60: GR | AJ60: 0 | AK60: 0 | AL60: IT | AM60: 0564898376 - 3409412240 | AN60: tabaccheria.murri@gmail.com; | AO60: -
A61: 99014915 | B61: M & M DI LASTRA MARCELLO & C. S.A.S. | C61: 01585820663 | D61: LSTMCL65S10I804E | E61: SARDI - 67039 SULMONA | F61: Y | H61: ITCD0C0806S0001 | I61: M & M DI LASTRA MARCELLO & C. SAS | J61: 01585820663 | K61: 105102 | L61: AQ | M61: 01585820663 | N61: VIA SARDI GENNARO 66 | O61: 67039 | P61: SULMONA | R61: AQ | S61: ABRUZZO | T61: Attiva | U61: SOCIETA' IN ACCOMANDITA SEMPLICE | V61: SOCIETA' DI PERSONE | X61: LASTRA | Y61: MARCELLO | Z61: M | AA61: 10/11/1965 | AB61: AQ | AC61: SULMONA | AD61: IT | AF61: VIALE STAZIONE 46/A | AG61: 67039 | AH61: SULMONA | AI61: AQ | AM61: 3404013032 | AN61: BARSARDI.SULMONA@GMAIL.COM; | AO61: -
A62: 99014610 | B62: PUNTO SNAI NUORO SRLS | C62: 01593770918 | D62: 01593770918 | E62: ATTILIO DEFFENU - 08100 NUORO | F62: Y | H62: ITE35F0307S0001 | I62: PUNTO SNAI NUORO S.R.L.S. | J62: 01593770918 | K62: 113783 | L62: NU | M62: 01593770918 | N62: VIA ATTILIO DEFFENU 117 | O62: 08100 | P62: NUORO | R62: NU | S62: SARDEGNA | T62: Inattiva | U62: SOCIETA' A RESPONSABILITA' LIMITATA SEMPLIFICATA | V62: SOCIETA' DI CAPITALE | X62: PATTERI | Y62: GIOVANNI | Z62: M | AA62: 03/12/1950 | AB62: NU | AC62: DORGALI | AD62: IT | AE62: 0 | AF62: VIA BUDAPEST 8 | AG62: 07100 | AH62: SASSARI | AI62: SS | AJ62: 0 | AK62: 0 | AL62: IT | AM62: 3484083475 | AN62: puntosnainuoro@gmail.com; | AO62: -
A63: 99013233 | B63: SUPREMIA SRL | C63: 01603020551 | D63: 01603020551 | E63: PIAZZA DEI CONSOLI 56 00175 ROMA (RM) | F63: Y | H63: ITD194080ES0001 | I63: SUPREMIA SRL | J63: 01603020551 | K63: 1562550 | L63: RM | M63: 01603020551 | N63: PIAZZA DEI CONSOLI 56 | O63: 00175 | P63: ROMA | R63: RM | S63: LAZIO | T63: Attiva | U63: SOCIETA' A RESPONSABILITA' LIMITATA | V63: SOCIETA' DI CAPITALE | X63: SALVATI | Y63: FRANCESCA | Z63: F | AA63: 31/10/1976 | AB63: TR | AC63: TERNI | AD63: IT | AE63: 0 | AF63: STRADA DI COSPEA 28 | AG63: 05100 | AH63: TERNI | AI63: TR | AJ63: 0 | AK63: 0 | AL63: IT | AM63: 06-76967768 - 3477476393 | AN63: SUPREMIA@LIBERO.IT; | AO63: -
A64: 99012298 | B64: NOVA SLOT SAS DI ZHOU GUOQIAO E C | C64: 01623570056 | D64: 01623570056 | E64: VIA GUIDO GOZZANO 7 - 14100 ASTI AT | F64: Y | H64: IT6C9F0E0ES0001 | I64: NOVA SLOT SAS DI ZHOU GUOQIAO E C. | J64: 01623570056 | K64: 130187 | L64: AT | M64: 01623570056 | N64: VIA GUIDO GOZZANO 7 | O64: 14100 | P64: ASTI | R64: AT | S64: PIEMONTE | T64: Attiva | U64: SOCIETA' IN ACCOMANDITA SEMPLICE | V64: SOCIETA' DI PERSONE | X64: ZHOU | Y64: GUOQIAO | Z64: M | AA64: 07/10/1980 | AB64: E | AC64: CINA | AD64: CN | AE64: CINA | AF64: VIA ROMA 20/C | AG64: 24030 | AH64: VALBREMBO | AI64: BG | AJ64: 0 | AK64: 0 | AL64: IT | AM64: 3471191819 | AN64: ivansas168@gmail.com; | AO64: -
A65: 99014493 | B65: BAR PIERETTI SNC DI SALIMBENI LORIS E C | C65: 01627510561 | D65: 01627510561 | E65: ORVIETANA - 01027 MONTEFIASCONE | F65: Y | H65: IT7800050ES0001 | I65: BAR PIERETTI SNC DI SALIMBENI LORIS E C. | J65: 01627510561 | K65: 117815 | L65: VT | M65: 01627510561 | N65: VIA ORVIETANA 3 | O65: 01027 | P65: MONTEFIASCONE | R65: VT | S65: LAZIO | T65: Attiva | U65: SOCIETA' IN NOME COLLETTIVO | V65: SOCIETA' DI PERSONE | X65: SALIMBENI | Y65: LORIS | Z65: M | AA65: 05/10/1961 | AB65: VT | AC65: VITERBO | AD65: IT | AE65: 0 | AF65: VIA DELLE MIMOSE 24 | AG65: 01030 | AH65: VITORCHIANO | AI65: VT | AJ65: 0 | AK65: 0 | AL65: 0 | AM65: 0761 971287 | AN65: LORIS.50@HOTMAIL.IT; | AO65: -
A66: 99001374 | B66: BAR LA VILLA SAS | C66: 01646700607 | D66: TNZNGL60C14C413I | E66: VIA SAN SEBASTIANO, 52 - 03023 CECCANO FR | F66: Y | H66: IT90290907S0001 | I66: TANZINI ANGELO | J66: 01923270605 | K66: 112674 | L66: FR | M66: TNZNGL60C14C413I | N66: PIAZZA MUNICIPIO 1 | O66: 03023 | P66: CECCANO | R66: FR | S66: LAZIO | T66: Attiva | U66: IMPRESA INDIVIDUALE | V66: IMPRESE INDIVIDUALI | X66: TANZINI | Y66: ANGELO | Z66: M | AA66: 14/03/1960 | AB66: FR | AC66: CECCANO | AD66: IT | AE66: 0 | AF66: VIA MADONNA DEL CARMINE 25 | AG66: 03023 | AH66: CECCANO | AI66: FR | AJ66: 0 | AK66: 0 | AL66: 0 | AM66: 0775 625082 | AN66: ccarlini.professional@gmail.com; | AO66: -
A67: 99012176 | B67: BAR JOLLY DI JI LAFAN | C67: 01650480195 | D67: JIXLFN93A62Z210D | E67: VIA TIZIANO VECELLIO 78 - 35132 PADOVA PD | F67: Y | H67: IT749F000ES0001 | I67: BAR JOLLY DI JI LAFAN | J67: 01650480195 | K67: 436913 | L67: PD | M67: JIXLFN93A62Z210D | N67: VIA TIZIANO VECELLIO 78 | O67: 35132 | P67: PADOVA | R67: PD | S67: VENETO | T67: Attiva | U67: IMPRESA INDIVIDUALE | V67: IMPRESE INDIVIDUALI | X67: JI | Y67: LAFAN | Z67: F | AA67: 22/01/1993 | AB67: E | AC67: CINA | AD67: CN | AE67: CINA | AF67: VIA ENRICO PETRELLA 2 | AG67: 35132 | AH67: PADOVA | AI67: PD | AJ67: 0 | AK67: 0 | AL67: IT | AM67: 0498648239 - 3663932041 | AN67: emysing222@gmail.com; | AO67: -
A68: 99014730 | B68: MAZZUCCONI VINCENZO | C68: 01651590554 | D68: MZZVCN65P08H501L | E68: G. MAZZINI - 05032 CALVI DELL'UMBRIA | F68: Y | H68: ITC95D020AS0001 | I68: MAZZUCCONI VINCENZO | J68: 01651590554 | K68: 113896 | L68: TR | M68: MZZVCN65P08H501L | N68: PIAZZA GIUSEPPE MAZZINI 13 | O68: 05032 | P68: CALVI DELL'UMBRIA | R68: TR | S68: UMBRIA | T68: Attiva | U68: IMPRESA INDIVIDUALE | V68: IMPRESE INDIVIDUALI | X68: MAZZUCCONI | Y68: VINCENZO | Z68: M | AA68: 08/09/1965 | AB68: RM | AC68: ROMA | AD68: IT | AE68: 0 | AF68: VIA DELLA COLLEGGIATA 1 | AG68: 05032 | AH68: CALVI DELL'UMBRIA | AI68: TR | AJ68: 0 | AK68: 0 | AL68: IT | AM68: 3533709992 | AN68: VINCENZOMAZZUCCONI@GMAIL.COM; | AO68: -
A69: 99008057 | B69: DI MARCO FABRIZIO & C. S.A.S. | C69: 01675110686 | D69: 01675110686 | E69: VIA G. DI MARZIO 19 - 65010 SPOLTORE PE | F69: Y | H69: IT7260060CS0001 | I69: DI MARCO FABRIZIO & C. SAS | J69: 01675110686 | K69: 120144 | L69: PE | M69: 01675110686 | N69: VIA DI MARZIO GIOACCHINO 19 | O69: 65010 | P69: SPOLTORE | R69: PE | S69: ABRUZZO | T69: Attiva | U69: SOCIETA' IN ACCOMANDITA SEMPLICE | V69: SOCIETA' DI PERSONE | X69: DI MARCO | Y69: FABRIZIO | Z69: M | AA69: 27/12/1964 | AB69: PE | AC69: PESCARA | AD69: IT | AE69: 0 | AF69: VIA GRADINATA 2 | AG69: 65010 | AH69: SPOLTORE | AI69: PE | AJ69: 0 | AK69: 0 | AL69: 0 | AM69: 3298654144 - 0854962656 | AN69: marcodimarco10@hotmail.it; | AO69: -
A70: 99015510 | B70: PR GIOCHI SRLS | C70: 01676140559 | D70: 01676140559 | E70: VILLAFRANCA - 05100 TERNI | F70: Y | H70: ITD9DC0A0DS0001 | I70: PR GIOCHI SRL SEMPLIFICATA | J70: 01676140559 | K70: 353683 | L70: TR | M70: 01676140559 | N70: VIALE VILLAFRANCA 7 | O70: 05100 | P70: TERNI | R70: TR | S70: UMBRIA | T70: Attiva | U70: SOCIETA' A RESPONSABILITA' LIMITATA SEMPLIFICATA | V70: SOCIETA' DI CAPITALE | X70: PROIETTI | Y70: RICCARDO | Z70: M | AA70: 01/06/1969 | AB70: TR | AC70: TERNI | AD70: IT | AE70: 0 | AF70: VIA DEL RIVO 119 | AG70: 05100 | AH70: TERNI | AI70: TR | AJ70: 0 | AK70: 0 | AL70: 0 | AM70: 3478443264 | AN70: PRGIOCHISRLS@GMAIL.COM; | AO70: -
A71: 99012520 | B71: NUMBER ONE BET SRL | C71: 01677310623 | D71: 01677310623 | E71: VIA CUPA DELL'ANGELO 6 - 82100 BENEVENTO | F71: Y | H71: IT6C99030ES0001 | I71: NUMBER ONE BET SRL | J71: 01677310623 | K71: 139534 | L71: BN | M71: 01677310623 | N71: VIA CUPA DELL'ANGELO 2-4-6 | O71: 82100 | P71: BENEVENTO | R71: BN | S71: CAMPANIA | T71: Attiva | U71: SOCIETA' A RESPONSABILITA' LIMITATA | V71: SOCIETA' DI CAPITALE | X71: TEDESCO | Y71: GERARDO | Z71: M | AA71: 17/11/1964 | AB71: BN | AC71: MONTESARCHIO | AD71: IT | AE71: 0 | AF71: VIA LORENZONI 22 | AG71: 82013 | AH71: BONEA | AI71: BN | AJ71: 0 | AK71: 0 | AL71: IT | AM71: 3939547988 MI - 3314116371 | AN71: snaibenevento@libero.it; roccorosato2006@libero.it | AO71: -
A72: 99015479 | B72: DIQUATTRO GIUSEPPA | C72: 01678580885 | D72: DQTGPP62C58H163X | E72: PORTUENSE - 00148 ROMA | F72: Y | H72: IT6C550E01S0001 | I72: DIQUATTRO GIUSEPPA | J72: 01678580885 | K72: 1589016 | L72: RM | M72: DQTGPP62C58H163X | N72: VIA PORTUENSE 774 | O72: 00148 | P72: ROMA | R72: RM | S72: LAZIO | T72: Attiva | U72: IMPRESA INDIVIDUALE | V72: IMPRESE INDIVIDUALI | X72: DIQUATTRO | Y72: GIUSEPPA | Z72: F | AA72: 18/03/1962 | AB72: RG | AC72: RAGUSA | AD72: IT | AE72: 0 | AF72: VIA PORTUENSE 681 | AG72: 00149 | AH72: ROMA | AI72: RM | AJ72: 0 | AK72: 0 | AL72: IT | AM72: 06-65671331 | AN72: tabaccheriadiquattro@gmail.com; | AO72: -
A73: 99013440 | B73: LO PRESTI CLAUDIA | C73: 01700650888 | D73: LPRCLD84M45M088E | E73: VIA ADUA 11 A, 97019, VITTORIA (RG) | F73: Y | H73: IT3F9F0909S0001 | I73: LO PRESTI CLAUDIA | J73: 01700650888 | K73: 415561 | L73: RG | M73: LPRCLD84M45M088E | N73: VIA ADUA 11 A | O73: 97019 | P73: VITTORIA | R73: RG | S73: SICILIA | T73: Attiva | U73: IMPRESA INDIVIDUALE | V73: IMPRESE INDIVIDUALI | X73: LO PRESTI | Y73: CLAUDIA | Z73: F | AA73: 05/08/1984 | AB73: RG | AC73: VITTORIA | AD73: 0 | AE73: 0 | AF73: VIA GIOVANNI AMENDOLA 44 A | AG73: 97019 | AH73: VITTORIA | AI73: RG | AJ73: 0 | AK73: 0 | AL73: IT | AM73: 3935299978 | AN73: claudialopresti19@virgilio.it; | AO73: -
A74: 99002464 | B74: BIANCO GIANLUCA | C74: 01702630789 | D74: BNCGLC69R10A041R | E74: CONTRADA MACCHIA 47 - 87020 ACQUAPPESA CS | F74: Y | H74: IT86860C06S0001 | I74: BIANCO GIANLUCA | J74: 01702630789 | K74: 112268 | L74: CS | M74: BNCGLC69R10A041R | N74: CONTRADA MACCHIA 25 | O74: 87020 | P74: ACQUAPPESA | R74: CS | S74: CALABRIA | T74: Attiva | U74: IMPRESA INDIVIDUALE | V74: IMPRESE INDIVIDUALI | X74: Bianco | Y74: Gianluca | Z74: M | AA74: 10/10/1969 | AB74: CS | AC74: ACQUAPPESA | AD74: IT | AE74: 0 | AF74: CONTRADA MACCHIA 47 | AG74: 87020 | AH74: ACQUAPPESA | AI74: CS | AJ74: 0 | AK74: 0 | AL74: 0 | AM74: 098294574 - 3485122527 | AN74: gianbianco@libero.it; | AO74: -
A75: 99001436 | B75: LEVRATTO BARBARA | C75: 01703900991 | D75: LVRBBR80A57D969O | E75: VIA CAVOUR 50 - 12074 CORTEMILIA CN | F75: Y | G75: Y | H75: ITBC840204S0001 | I75: LEVRATTO BARBARA | J75: 01703900991 | K75: 267507 | L75: CN | M75: LVRBBR80A57D969O | N75: VIA CAVOUR 50 | O75: 12074 | P75: CORTEMILIA | R75: CN | S75: PIEMONTE | T75: Attiva | U75: IMPRESA INDIVIDUALE | V75: IMPRESE INDIVIDUALI | X75: LEVRATTO | Y75: BARBARA | Z75: F | AA75: 17/01/1980 | AB75: GE | AC75: GENOVA | AD75: IT | AE75: 0 | AF75: REGIONE BERGAMASCHI 3 | AG75: 12074 | AH75: BERGOLO | AI75: CN | AJ75: LOCALITA' | AK75: 0 | AL75: IT | AM75: 017381209 - 3386233768 | AN75: levratto.barbara@libero.it; | AO75: -
A76: 99001436 | B76: LEVRATTO BARBARA | C76: 01703900991 | D76: LVRBBR80A57D969O | E76: VIA CAVOUR 50 - 12074 CORTEMILIA CN | F76: Y | G76: Y | H76: ITBC840204S0001 | I76: LEVRATTO BARBARA | J76: 01703900991 | K76: 267507 | L76: CN | M76: LVRBBR80A57D969O | N76: VIA CAVOUR 50 | O76: 12074 | P76: CORTEMILIA | R76: CN | S76: PIEMONTE | T76: Attiva | U76: IMPRESA INDIVIDUALE | V76: IMPRESE INDIVIDUALI | X76: LEVRATTO | Y76: BARBARA | Z76: F | AA76: 17/01/1980 | AB76: GE | AC76: GENOVA | AD76: IT | AE76: 0 | AF76: REGIONE BERGAMASCHI 3 | AG76: 12074 | AH76: BERGOLO | AI76: CN | AJ76: LOCALITA' | AK76: 0 | AL76: IT | AM76: 017381209 - 3386233768 | AN76: levratto.barbara@libero.it; | AO76: -
A77: 99015535 | B77: TONY&ALE GAMES S.R.L.S. | C77: 01705700050 | D77: TONY&ALE GA | E77: PARTIGIANI - 14100 ASTI | F77: Y | H77: IT89D10303S0001 | I77: TONY&ALE GAMES SRL SEMPLIFICATA | J77: 01705700050 | K77: 304103 | L77: AT | M77: 01705700050 | N77: VIALE DEI PARTIGIANI 115 | O77: 14100 | P77: ASTI | R77: AT | S77: PIEMONTE | T77: Attiva | U77: SOCIETA' A RESPONSABILITA' LIMITATA SEMPLIFICATA | V77: SOCIETA' DI CAPITALE | X77: NAVA | Y77: ALESSANDRO | Z77: M | AA77: 14/07/1996 | AB77: AT | AC77: ASTI | AD77: 0 | AE77: 0 | AF77: VIALE DEI PARTIGIANI 115 | AG77: 14100 | AH77: ASTI | AI77: AT | AJ77: 0 | AK77: 0 | AL77: IT | AM77: 3921181849 | AN77: Ale.nava1996@icloud.com; | AO77: -
A78: 99009391 | B78: EUROBAR DI SOFIA SNC DI LIANG XIAOJ | C78: 01719010934 | D78: 01719010934 | E78: VIALE GUGLIELMO MARCONI 26 - 33170 PORDENONE PN | F78: Y | H78: ITE6E60209S0001 | I78: EUROBAR DI SOFIA SNC DI LIANG XIAOJIE & C. | J78: 01719010934 | K78: 99027 | L78: PN | M78: 01719010934 | N78: VIA GUGLIELMO MARCONI 26 | O78: 33070 | P78: BRUGNERA | R78: PN | S78: FRIULI-VENEZIA GIULIA | T78: Attiva | U78: SOCIETA' IN NOME COLLETTIVO | V78: SOCIETA' DI PERSONE | X78: DONG | Y78: CHENGHUI | Z78: M | AA78: 27/09/1986 | AB78: E | AC78: CINA | AD78: CN | AE78: CINA | AF78: VIALE MICHELANGELO GRIGOLETTI 48 | AG78: 33170 | AH78: PORDENONE | AI78: PN | AJ78: 0 | AK78: 0 | AL78: IT | AM78: 0434209145 - 3313989699 | AN78: snaieurobar@outlook.it; | AO78: -
A79: 99012466 | B79: CMV SRL | C79: 01738310331 | D79: 01738310331 | E79: VIA EGIDIO GORRA 55/D 29122 PIACENZA (PC) | F79: Y | H79: IT629C0607S0001 | I79: CMV SRL | J79: 01738310331 | K79: 187526 | L79: PC | M79: 01738310331 | N79: VIALE DEI MILLE 3 | O79: 29121 | P79: PIACENZA | R79: PC | S79: EMILIA-ROMAGNA | T79: Attiva | U79: SOCIETA' A RESPONSABILITA' LIMITATA | V79: SOCIETA' DI CAPITALE | X79: LEKA | Y79: EJELL | Z79: M | AA79: 16/07/1995 | AB79: E | AC79: LEZH | AD79: AL | AE79: ALBANIA | AF79: VIA AST 4 | AG79: 29121 | AH79: PIACENZA | AI79: PC | AJ79: 0 | AK79: 0 | AL79: IT | AM79: 02-8266845 - 370-3308202 | AN79: ageopera@outlook.it; ageromeo@outlook.it | AO79: -
A80: 99013006 | B80: C.M. SRL | C80: 01742610338 | D80: 01742610338 | E80: VIA MARTIRI DELLA BETTOLA, 20/G/H/I, 42123 REGGIO NELL'EMILIA (RE) | F80: Y | H80: IT96990408S0001 | I80: C.M. SRL | J80: 01742610338 | K80: 314620 | L80: RE | M80: 01742610338 | N80: VIA MARTIRI DELLA BETTOLA 20/G/H/I | O80: 42123 | P80: REGGIO NELL'EMILIA | R80: RE | S80: EMILIA-ROMAGNA | T80: Attiva | U80: SOCIETA' A RESPONSABILITA' LIMITATA | V80: SOCIETA' DI CAPITALE | X80: QIU LIN | Y80: RU YI | Z80: F | AA80: 15/04/1998 | AB80: RE | AC80: REGGIO EMILIA | AD80: IT | AE80: 0 | AF80: VIA MARTIRI DELLA BETTOLA 8 | AG80: 42123 | AH80: REGGIO NELL'EMILIA | AI80: RE | AJ80: 0 | AK80: 0 | AL80: IT | AM80: 0522-1932127 - 370-3308202 | AN80: CMSRL2016@LIBERO.IT; cmsrl.marcofra@gmail.com | AO80: -
A81: 99001487 | B81: TECNOGIOCHI DI MAGELLI FABIO | C81: 01748430970 | D81: MGLFBA65B14G999Q | E81: VIA SCARPETTINI, 102 - 59013 MONTEMURLO | F81: Y | H81: IT540B0F0CS0001 | I81: TECNOGIOCHI DI MAGELLI FABIO | J81: 01748430970 | K81: 467337 | L81: PO | M81: MGLFBA65B14G999Q | N81: VIA RAFFAELLO SCARPETTINI 102 | O81: 59013 | P81: MONTEMURLO | R81: PO | S81: TOSCANA | T81: Attiva | U81: IMPRESA INDIVIDUALE | V81: IMPRESE INDIVIDUALI | X81: MAGELLI | Y81: FABIO | Z81: M | AA81: 14/02/1965 | AB81: PO | AC81: PRATO | AD81: IT | AE81: 0 | AF81: VIA RAFFAELLO SCARPETTINI 25 | AG81: 59013 | AH81: MONTEMURLO | AI81: PO | AJ81: 0 | AK81: 0 | AL81: IT | AM81: 0574689317 - 3476387535 | AN81: tecnogiochi@hotmail.com; | AO81: -
A82: 99015126 | B82: NIGITA BIAGIO | C82: 01749030886 | D82: NGTBGI73D15C927R | E82: SAN FRANCESCO - 97013 COMISO | F82: Y | H82: ITE7520F0CS0001 | I82: NIGITA BIAGIO | J82: 01749030886 | K82: 434056 | L82: RG | M82: NGTBGI73D15C927R | N82: PIAZZA SAN FRANCESCO 10 | O82: 97013 | P82: COMISO | R82: RG | S82: SICILIA | T82: Attiva | U82: IMPRESA INDIVIDUALE | V82: IMPRESE INDIVIDUALI | X82: NIGITA | Y82: BIAGIO | Z82: M | AA82: 15/04/1973 | AB82: RG | AC82: COMISO | AD82: 0 | AE82: 0 | AF82: VIALE PAPA GIOVANNI PAOLO II 10 | AG82: 97013 | AH82: COMISO | AI82: RG | AJ82: 0 | AK82: 0 | AL82: IT | AM82: 3398009717 | AN82: tabacchinigita@gmail.com; | AO82: -
A83: 99014348 | B83: PLANET BET ITALIA S.R.L.S. | C83: 01755070628 | D83: 01755070628 | E83: CALORE - 82031 AMOROSI | F83: Y | H83: ITC2530C05S0001 | I83: PLANET BET ITALIA S.R.L.S. | J83: 01755070628 | K83: 145776 | L83: BN | M83: 01755070628 | N83: VIA CALORE 23 | O83: 82031 | P83: AMOROSI | R83: BN | S83: CAMPANIA | T83: Attiva | U83: SOCIETA' A RESPONSABILITA' LIMITATA SEMPLIFICATA | V83: SOCIETA' DI CAPITALE | X83: CIERVO | Y83: GIANLUCA | Z83: M | AA83: 23/11/1979 | AB83: BN | AC83: DUGENTA | AD83: IT | AE83: 0 | AF83: VIA NAZIONALE 44 | AG83: 82030 | AH83: DUGENTA | AI83: BN | AJ83: 0 | AK83: 0 | AL83: IT | AM83: 3476885819 | AN83: enzo.ciervo@libero.it; | AO83: -
A84: 99005870 | B84: EURO BAR SAS DI ZINO DARIO E C. | C84: 01755880034 | D84: 01755880034 | E84: VIA DE ANGELI 7, 28887, OMEGNA (VB) , IT | F84: Y | H84: ITAF860E00S0001 | I84: EURO BAR SAS DI ZINO DARIO E C. | J84: 01755880034 | K84: 187243 | L84: VB | M84: 01755880034 | N84: VIA DE ANGELI 7 | O84: 28887 | P84: OMEGNA | R84: VB | S84: PIEMONTE | T84: Attiva | U84: SOCIETA' IN ACCOMANDITA SEMPLICE | V84: SOCIETA' DI PERSONE | X84: ZINO | Y84: DARIO | Z84: M | AA84: 31/05/1985 | AB84: VB | AC84: OMEGNA | AD84: IT | AE84: 0 | AF84: PIAZZA CAMILLO CAVOUR 22 | AG84: 28921 | AH84: VERBANIA | AI84: VB | AJ84: 0 | AK84: 0 | AL84: IT | AM84: - | AN84: - | AO84: -
A85: 99015606 | B85: BULLDOG CAFFE' DI TORKI HANI | C85: 01760470193 | D85: TRKHNA86R01Z336N | E85: CRISPI - 26013 CREMA | F85: Y | H85: IT85D00E04S0001 | I85: BULLDOG CAFFE' DI TORKI HANI | J85: 01760470193 | K85: 199299 | L85: CR | M85: TRKHNA86R01Z336N | N85: VIA FRANCESCO CRISPI 20 | O85: 26013 | P85: CREMA | R85: CR | S85: LOMBARDIA | T85: Attiva | U85: IMPRESA INDIVIDUALE | V85: IMPRESE INDIVIDUALI | X85: TORKI | Y85: HANI | Z85: M | AA85: 01/10/1986 | AB85: E | AC85: EGITTO | AD85: EG | AE85: ITALIA | AF85: VIA MONSIGNORE ANDREA CAPPELLAZZI 1 A | AG85: 26013 | AH85: CREMA | AI85: CR | AJ85: 0 | AK85: 0 | AL85: IT | AM85: 3396077555 | AN85: hany.torky@yahoo.it; | AO85: -
A86: 99015608 | B86: ITA NOLEGGIO DI CHEN DONGLIN | C86: 01761810199 | D86: CHNDGL69A22Z210V | E86: DANTE CHIASSERINI - 20157 MILANO | F86: Y | H86: IT93D80A00S0001 | I86: ITA NOLEGGIO DI CHEN DONGLIN | J86: 01761810199 | K86: 2640830 | L86: MI | M86: CHNDGL69A22Z210V | N86: VIA DANTE CHIASSERINI 107 | O86: 20157 | P86: MILANO | R86: MI | S86: LOMBARDIA | T86: Attiva | U86: IMPRESA INDIVIDUALE | V86: IMPRESE INDIVIDUALI | X86: CHEN | Y86: DONGLIN | Z86: M | AA86: 22/01/1969 | AB86: E | AC86: CINA | AD86: CN | AE86: CINA | AF86: VIA FABIO FILZI 150 | AG86: 26100 | AH86: CREMONA | AI86: CR | AJ86: 0 | AK86: 0 | AL86: IT | AM86: 3488195920 | AN86: alessiahu86@hotmail.com; | AO86: -
A87: 99013423 | B87: LAS VEGAS GOLD SRL | C87: 01763100334 | D87: 01763100334 | E87: LOCALITA' FORNACE, 35, 29010 CASTELVETRO PIACENTINO (PC | F87: Y | H87: IT6D9F0F0BS0001 | I87: LAS VEGAS GOLD SRL | J87: 01763100334 | K87: 189476 | L87: PC | M87: 01763100334 | N87: LOCALITA' FORNACE 35 | O87: 29010 | P87: CASTELVETRO PIACENTINO | R87: PC | S87: EMILIA-ROMAGNA | T87: Attiva | U87: SOCIETA' A RESPONSABILITA' LIMITATA | V87: SOCIETA' DI CAPITALE | X87: XU | Y87: RICHENG | Z87: M | AA87: 12/07/1990 | AB87: E | AC87: CINA | AD87: CN | AE87: CINA | AF87: VIA DEI TESSITORI 1 | AG87: 60035 | AH87: JESI | AI87: AN | AJ87: 0 | AK87: 0 | AL87: IT | AM87: 0372-27008 - 392-2259637 | AN87: lasvegasgoldsrl.cremona@gmail.com; | AO87: -
A88: 99013801 | B88: ZHENG H24 S.R.L.S. | C88: 01763700331 | D88: 01763700331 | E88: MAESTRI DEL LAVORO - 29122 PIACENZA | F88: Y | H88: ITE3930200S0001 | I88: ZHENG H24 SRL SEMPLIFICATA ENUNCI ABILE ANCHE ZHENG H24 SRL S | J88: 01763700331 | K88: 189512 | L88: PC | M88: 01763700331 | N88: VIA MAESTRI DEL LAVORO 7 | O88: 29122 | P88: PIACENZA | R88: PC | S88: EMILIA-ROMAGNA | T88: Attiva | U88: SOCIETA' A RESPONSABILITA' LIMITATA SEMPLIFICATA | V88: SOCIETA' DI CAPITALE | X88: ZHENG | Y88: GUOHUA | Z88: M | AA88: 23/02/1996 | AB88: TA | AC88: TARANTO | AD88: 0 | AE88: 0 | AF88: VIA RIVO 9 | AG88: 43015 | AH88: NOCETO | AI88: PR | AJ88: 0 | AK88: 0 | AL88: IT | AM88: 3884884877 | AN88: fabiozeng96@hotmail.it; | AO88: -
A89: 99013641 | B89: LAS VEGAS HU SRL | C89: 01773790090 | D89: 01773790090 | E89: CORSO BRIGATE PARTIGIANE 13/E 17014 CAIRO MONTENOTTE (SV) | F89: Y | H89: IT93900E07S0001 | I89: LAS VEGAS HU SRL | J89: 01773790090 | K89: 212183 | L89: SV | M89: 01773790090 | N89: CORSO BRIGATE PARTIGIANE 13/E | O89: 17014 | P89: CAIRO MONTENOTTE | R89: SV | S89: LIGURIA | T89: Attiva | U89: SOCIETA' A RESPONSABILITA' LIMITATA | V89: SOCIETA' DI CAPITALE | X89: HU | Y89: LISHE | Z89: M | AA89: 10/06/1984 | AB89: E | AC89: CINA | AD89: CN | AE89: CINA | AF89: VIA DON BARTOLOMEO GRAZIOLI 11 | AG89: 20161 | AH89: MILANO | AI89: MI | AJ89: 0 | AK89: 0 | AL89: IT | AM89: 3892583088 | AN89: lasvegashusrl@gmail.com; | AO89: -
A90: 99015238 | B90: AMBROSONE LUIGIA | C90: 01792720623 | D90: MBRLGU97L42A783Q | E90: NAPOLI PARCO EUROPA - 82016 MONTESARCHIO | F90: Y | H90: IT4CDB030ES0001 | I90: AMBROSONE LUIGIA | J90: 01792720623 | K90: 148729 | L90: BN | M90: MBRLGU97L42A783Q | N90: VIA NAPOLI PARCO EUROPA 74 | O90: 82016 | P90: MONTESARCHIO | R90: BN | S90: CAMPANIA | T90: Attiva | U90: IMPRESA INDIVIDUALE | V90: IMPRESE INDIVIDUALI | X90: AMBROSONE | Y90: LUIGIA | Z90: F | AA90: 02/07/1997 | AB90: BN | AC90: BENEVENTO | AD90: 0 | AE90: 0 | AF90: VIA NAPOLI 74 | AG90: 82016 | AH90: MONTESARCHIO | AI90: BN | AJ90: 0 | AK90: 0 | AL90: IT | AM90: 0824834088 | AN90: ILARIAORSETTO20@ICLOUD.COM; | AO90: -
A91: 99015138 | B91: LA ROSA DIEGO | C91: 01807120850 | D91: LRSDGI75A27F899Z | E91: BINDA D'AMBROGIO - 20143 MILANO | F91: Y | H91: IT7B0E090ES0001 | I91: LA ROSA DIEGO | J91: 01807120850 | K91: 1889228 | L91: MI | M91: LRSDGI75A27F899Z | N91: VIA AMBROGIO BINDA 45 | O91: 20143 | P91: MILANO | R91: MI | S91: LOMBARDIA | T91: Attiva | U91: IMPRESA INDIVIDUALE | V91: IMPRESE INDIVIDUALI | X91: LA ROSA | Y91: DIEGO | Z91: M | AA91: 27/01/1975 | AB91: CL | AC91: NISCEMI | AD91: IT | AE91: 0 | AF91: VIA GIOTTO 58 | AG91: 93015 | AH91: NISCEMI | AI91: CL | AJ91: 0 | AK91: 0 | AL91: 0 | AM91: - | AN91: cafebinda.45@gmail.com; | AO91: -
A92: 99014397 | B92: CM SPORT SRLS | C92: 01811780335 | D92: 01811780335 | E92: ABRUZZO - 29017 FIORENZUOLA D'ARDA | F92: Y | H92: IT9B52000DS0001 | I92: CM SPORT SRL SEMPLIFICATA ENUNC IABILE ANCHE CM SPORT S.R.L.S. | J92: 01811780335 | K92: 193194 | L92: PC | M92: 01811780335 | N92: VIA ABRUZZO 10/A-B | O92: 29017 | P92: FIORENZUOLA D'ARDA | R92: PC | S92: EMILIA-ROMAGNA | T92: Attiva | U92: SOCIETA' A RESPONSABILITA' LIMITATA SEMPLIFICATA | V92: SOCIETA' DI CAPITALE | X92: FENG | Y92: MIN | Z92: M | AA92: 13/01/1990 | AB92: E | AC92: CINA | AD92: CN | AE92: CINA | AF92: VIA CORREGGIO 423 | AG92: 44042 | AH92: CENTO | AI92: FE | AJ92: CASUMARO | AK92: 0 | AL92: IT | AM92: 3338843768 - 3496536943 | AN92: cmsportsrls@gmail.com; | AO92: -
A93: 99009849 | B93: OK GAMES SRL | C93: 01819410026 | D93: 01819410026 | E93: PIAZZA MAZZINI 25 - 13011 BORGOSESIA VC | F93: Y | H93: ITB8460F0BS0001 | I93: OK GAMES SRL | J93: 01819410026 | K93: 166082 | L93: VC | M93: 01819410026 | N93: PIAZZA GIUSEPPE MAZZINI 25 | O93: 13011 | P93: BORGOSESIA | R93: VC | S93: PIEMONTE | T93: Attiva | U93: SOCIETA' A RESPONSABILITA' LIMITATA | V93: SOCIETA' DI CAPITALE | X93: GUGLIELMI | Y93: DAVIDE | Z93: M | AA93: 12/08/1969 | AB93: CO | AC93: CANTU' | AD93: IT | AE93: 0 | AF93: VIA MAGGIORA 100/A | AG93: 28021 | AH93: BORGOMANERO | AI93: NO | AJ93: 0 | AK93: 0 | AL93: 0 | AM93: 0163432430 - 3386660975 | AN93: max2003_m@libero.it; | AO93: -
A94: 99007535 | B94: LA MONGOLFIERA DI SCREPANTE GIAN PA | C94: 01825770447 | D94: SCRGPL76E03F522C | E94: VIALE TRIESTE, 49 - 63845 PONZANO DI FERMO FM | F94: Y | H94: ITBE080C0BS0001 | I94: LA MONGOLFIERA DI SCREPANTE GIAN PAOLO | J94: 01825770447 | K94: 176503 | L94: FM | M94: SCRGPL76E03F522C | N94: VIA TRIESTE 49 | O94: 63845 | P94: PONZANO DI FERMO | R94: FM | S94: MARCHE | T94: Attiva | U94: IMPRESA INDIVIDUALE | V94: IMPRESE INDIVIDUALI | X94: SCREPANTE | Y94: GIAN PAOLO | Z94: M | AA94: 03/05/1976 | AB94: FM | AC94: MONTEGRANARO | AD94: IT | AE94: 0 | AF94: STRADA FONTE SAN PIETRO 7 | AG94: 63844 | AH94: GROTTAZZOLINA | AI94: FM | AJ94: 0 | AK94: 0 | AL94: IT | AM94: 3487967100 - 0734632794 | AN94: molletta@libero.it; | AO94: -
A95: 99013257 | B95: SPECA MARIANO | C95: 01841290677 | D95: SPCMRN71R05H769Z | E95: VIA CRISTOFORO COLOMBO 18, 64014, MARTINSICURO (TE) | F95: Y | H95: ITCEE10904S0001 | I95: SPECA MARIANO | J95: 01841290677 | K95: 157666 | L95: TE | M95: SPCMRN71R05H769Z | N95: VIA CRISTOFORO COLOMBO 18 | O95: 64014 | P95: MARTINSICURO | R95: TE | S95: ABRUZZO | T95: Attiva | U95: IMPRESA INDIVIDUALE | V95: IMPRESE INDIVIDUALI | X95: SPECA | Y95: MARIANO | Z95: M | AA95: 05/10/1971 | AB95: AP | AC95: SAN BENEDETTO DEL TRONTO | AD95: IT | AE95: 0 | AF95: VIA CRISTOFORO COLOMBO 14 | AG95: 64014 | AH95: MARTINSICURO | AI95: TE | AJ95: 0 | AK95: 0 | AL95: IT | AM95: 3498826338 | AN95: mspeca@tiscali.it; | AO95: -
A96: 99014390 | B96: TABACCHERIA MANTELLASSI ALICE | C96: 01844920494 | D96: MNTLCA94L71E625B | E96: GRANDE - 03530 LIVORNO | F96: Y | H96: ITFF16000AS0001 | I96: TABACCHERIA MANTELLASSI ALICE | J96: 01844920494 | K96: 163203 | L96: LI | M96: MNTLCA94L71E625B | N96: VIA GRANDE 25 | O96: 57123 | P96: LIVORNO | R96: LI | S96: TOSCANA | T96: Attiva | U96: IMPRESA INDIVIDUALE | V96: IMPRESE INDIVIDUALI | X96: MANTELLASSI | Y96: ALICE | Z96: F | AA96: 31/07/1994 | AB96: LI | AC96: LIVORNO | AD96: IT | AE96: 0 | AF96: VIA DELLA BASTIA 77 | AG96: 57122 | AH96: LIVORNO | AI96: LI | AJ96: 0 | AK96: 0 | AL96: IT | AM96: 338 6276458 | AN96: TABACCHERIAMANTELLASSI23@gmail.com; | AO96: -
A97: 99013031 | B97: TRIGNANI ELENA | C97: 01846720678 | D97: TRGLNE46P53A445H | E97: VIA GALILEO GALILEI 20/C - 64100 TERAMO | F97: Y | H97: ITA1E60401S0001 | I97: TRIGNANI ELENA | J97: 01846720678 | K97: 158490 | L97: TE | M97: TRGLNE46P53A445H | N97: VIA GALILEO GALILEI 20/C | O97: 64100 | P97: TERAMO | R97: TE | S97: ABRUZZO | T97: Attiva | U97: IMPRESA INDIVIDUALE | V97: IMPRESE INDIVIDUALI | X97: TRIGNANI | Y97: ELENA | Z97: F | AA97: 13/09/1946 | AB97: TE | AC97: ARSITA | AD97: IT | AE97: 0 | AF97: VIALE GALILEO GALILEI SNC | AG97: 64100 | AH97: TERAMO | AI97: TE | AJ97: SAN NICOLO' A TORDINO | AK97: 0 | AL97: IT | AM97: 0861-588700 - 348-3015157 | AN97: amministrazioneridolfisrl@gmail.com; | AO97: -
A98: 99009869 | B98: GARGIULO VINCENZO | C98: 01854240478 | D98: GRGVCN93C10L845I | E98: VIA GIUSEPPE GARIBALDI 43 - 51015 MONSUMMANO TERME PT | F98: Y | H98: IT96100F08S0001 | I98: GARGIULO VINCENZO | J98: 01854240478 | K98: 185062 | L98: PT | M98: GRGVCN93C10L845I | N98: VIA GIUSEPPE GARIBALDI 43 | O98: 51015 | P98: MONSUMMANO TERME | R98: PT | S98: TOSCANA | T98: Attiva | U98: IMPRESA INDIVIDUALE | V98: IMPRESE INDIVIDUALI | X98: GARGIULO | Y98: VINCENZO | Z98: M | AA98: 10/03/1993 | AB98: NA | AC98: VICO EQUENSE | AD98: IT | AE98: 0 | AF98: VIA PUCCINI 41 | AG98: 51010 | AH98: MASSA E COZZILE | AI98: PT | AJ98: 0 | AK98: 0 | AL98: IT | AM98: 57278334 - 3479201743 | AN98: gargiulo.vincenzo@yahoo.it; | AO98: -
A99: 99013936 | B99: MALTAGLIATI SIMONA | C99: 01863830475 | D99: MLTSMN65M56G491S | E99: MAZZINI - 00189 PESCIA | F99: Y | H99: ITB1100007S0001 | I99: MALTAGLIATI SIMONA | J99: 01863830475 | K99: 185940 | L99: PT | M99: MLTSMN65M56G491S | N99: PIAZZA MAZZINI 2 | O99: 51017 | P99: PESCIA | R99: PT | S99: TOSCANA | T99: Attiva | U99: IMPRESA INDIVIDUALE | V99: IMPRESE INDIVIDUALI | X99: MALTAGLIATI | Y99: SIMONA | Z99: F | AA99: 16/08/1965 | AB99: PT | AC99: PESCIA | AD99: IT | AE99: 0 | AF99: VIA PUCCINI 12 | AG99: 51010 | AH99: MASSA E COZZILE | AI99: PT | AJ99: 0 | AK99: 0 | AL99: 0 | AM99: 0572-476240 - 335352765 | AN99: anticatabaccheriatoscana@virgilio.it; | AO99: -
A100: 99009121 | B100: CHEN HANHAI | C100: 01865390437 | D100: CHNHNH90S10Z210D | E100: VIA INGANNI ANGELO 70 - 20147 MILANO MI | F100: Y | H100: ITB2170C06S0001 | I100: CHEN HANHAI | J100: 01865390437 | K100: 2049371 | L100: MI | M100: CHNHNH90S10Z210D | N100: VIA ANGELO INGANNI 70 | O100: 20147 | P100: MILANO | R100: MI | S100: LOMBARDIA | T100: Attiva | U100: IMPRESA INDIVIDUALE | V100: IMPRESE INDIVIDUALI | X100: CHEN | Y100: HANHAI | Z100: M | AA100: 10/11/1990 | AB100: E | AC100: CINA | AD100: CN | AE100: CINA | AF100: VIA ANGELO INGANNI 64 | AG100: 20147 | AH100: MILANO | AI100: MI | AJ100: 0 | AK100: 0 | AL100: IT | AM100: 02-419696 | AN100: bartoto@virgilio.it; | AO100: -
...

Sheet LegaliRappresentanti
A1: Codice Fiscale Esponente | B1: ﻿Crif Number | C1: Cognome Esponente | D1: Nome Esponente | E1: Sesso | F1: Data di nascita | G1: Provincia di Nascita | H1: Comune di Nascita | I1: Nazione di Nascita | J1: Cittadinanza | K1: Indirizzo | L1: CAP | M1: Comune | N1: Provincia | O1: Frazione | P1: Altre indicazioni | Q1: Nazione | R1: Telefono | S1: Email | T1: PEC
A2: PSQSLV99L53I403K | B2: IT000B080FS0001 | C2: PASQUAL | D2: SILVIA | E2: F | F2: 13/07/1999 | G2: PN | H2: SAN VITO AL TAGLIAMENTO | K2: VIA ALDO MORO 25 | L2: 33076 | M2: PRAVISDOMINI | N2: PN | Q2: IT | R2: - | S2: - | T2: - | U2: =VLOOKUP(A:A,'Imprese_File completo'!M:M,1,FALSE) -> #N/A
A3: PLMNLT71M58A285Y | B3: IT0016070ES0001 | C3: PALUMBO | D3: NICOLETTA | E3: F | F3: 18/08/1971 | G3: BA | H3: ANDRIA | I3: IT | K3: VIA ALESSANDRO MANZONI 12 | L3: 76123 | M3: ANDRIA | N3: BT | Q3: IT | R3: 3464047598 | S3: riki.vitale@gmail.com; | T3: snai.palumbo@pec.it | U3: =VLOOKUP(A:A,'Imprese_File completo'!M:M,1,FALSE) -> PLMNLT71M58A285Y
A4: LSCNTN73T08Z133Z | B4: IT00410605S0001 | C4: LA SCALIA | D4: ANTONIO | E4: M | F4: 08/12/1973 | G4: E | H4: SVIZZERA | I4: CH | J4: ITALIA | K4: VIA OSSOLA 5 | L4: 92024 | M4: CANICATTI' | N4: AG | Q4: IT | R4: - | S4: - | T4: - | U4: =VLOOKUP(A:A,'Imprese_File completo'!M:M,1,FALSE) -> #N/A
A5: PTRCGR73E07B602B | B5: IT00410605S0001 | C5: PITRUZZELLA | D5: CALOGERO | E5: M | F5: 07/05/1973 | G5: AG | H5: CANICATTI' | I5: IT | K5: CONTRADA FABRIZIO SNC | L5: 92024 | M5: CANICATTI' | N5: AG | Q5: IT | R5: - | S5: - | T5: - | U5: =VLOOKUP(A:A,'Imprese_File completo'!M:M,1,FALSE) -> #N/A
A6: WNGDYA97R28Z210K | B6: IT005C0E0BS0001 | C6: WANG | D6: DAYU | E6: M | F6: 28/10/1997 | G6: E | H6: CINA | I6: CN | J6: CINA | K6: VIA VITTORIO VENETO 156 | L6: 52100 | M6: AREZZO | N6: AR | Q6: IT | R6: - | S6: - | T6: - | U6: =VLOOKUP(A:A,'Imprese_File completo'!M:M,1,FALSE) -> #N/A
A7: PMPFNC78D66F870A | B7: IT01120C04S0001 | C7: POMPEI | D7: FRANCESCA | E7: F | F7: 26/04/1978 | G7: TE | H7: NERETO | I7: IT | K7: VIA ANTONIO CANOVA 9 | L7: 64016 | M7: SANT'EGIDIO ALLA VIBRATA | N7: TE | Q7: IT | R7: 3935513952 | S7: pompeifrancesca@alice.it; | T7: - | U7: =VLOOKUP(A:A,'Imprese_File completo'!M:M,1,FALSE) -> PMPFNC78D66F870A
A8: SLAGNN68H23C783Q | B8: IT01140F07S0001 | C8: SAULI | D8: GIOVANNI MARIA | E8: M | F8: 23/06/1968 | G8: AQ | H8: CIVITELLA ROVETO | I8: IT | K8: VIA DELLE ROSE 1 | L8: 67054 | M8: CIVITELLA ROVETO | N8: AQ | Q8: IT | R8: - | S8: - | T8: - | U8: =VLOOKUP(A:A,'Imprese_File completo'!M:M,1,FALSE) -> #N/A
A9: SSSLPN67S66H264V | B9: IT01190703S0001 | C9: SASSONE | D9: LIDIA PINA | E9: F | F9: 26/11/1967 | G9: MI | H9: RHO | I9: IT | K9: CORSO GARIBALDI 107 | L9: 85038 | M9: SENISE | N9: PZ | Q9: IT | R9: - | S9: - | T9: - | U9: =VLOOKUP(A:A,'Imprese_File completo'!M:M,1,FALSE) -> #N/A
A10: CNIMCN75L31G273R | B10: IT011D020DS0001 | C10: IACONA | D10: MARCANTONIO | E10: M | F10: 31/07/1975 | G10: PA | H10: PALERMO | I10: IT | K10: VIA CAPPUCCINI 317 | L10: 90129 | M10: PALERMO | N10: PA | Q10: IT | R10: 091-6166979 - 320-0746369 | S10: snaimendola58@libero.it; | T10: iaconamarcantonio@pec.confcommercio.pa.it | U10: =VLOOKUP(A:A,'Imprese_File completo'!M:M,1,FALSE) -> CNIMCN75L31G273R
A11: CSNCRN87A68D122Y | B11: IT015C010BS0001 | C11: COSENTINO | D11: CATERINA | E11: F | F11: 28/01/1987 | G11: KR | H11: CROTONE | I11: IT | K11: VIA RIALTO 47 | L11: 35020 | M11: BRUGINE | N11: PD | Q11: IT | R11: - | S11: - | T11: - | U11: =VLOOKUP(A:A,'Imprese_File completo'!M:M,1,FALSE) -> #N/A
A12: XIALGL90A48Z210S | B12: IT015C0D0AS0001 | C12: XIA | D12: LINGLING | E12: F | F12: 08/01/1990 | G12: E | H12: CINA | I12: CN | J12: CINA | K12: VIA SANT'ANTONIO 26 | L12: 55049 | M12: VIAREGGIO | N12: LU | Q12: IT | R12: - | S12: - | T12: - | U12: =VLOOKUP(A:A,'Imprese_File completo'!M:M,1,FALSE) -> #N/A
A13: HUXYNU87A05Z210Q | B13: IT01940104S0001 | C13: HU | D13: YUNAO | E13: M | F13: 05/01/1987 | G13: E | H13: ZHEJIANG | I13: CN | J13: CINA | K13: VIA NAZARIO SAURO 12 | L13: 21010 | M13: BESNATE | N13: VA | Q13: IT | R13: - | S13: - | T13: - | U13: =VLOOKUP(A:A,'Imprese_File completo'!M:M,1,FALSE) -> #N/A
A14: TRVNNA60P41F646F | B14: IT01980800S0001 | C14: TRAVAGLINI | D14: ANNA | E14: F | F14: 01/09/1960 | G14: PE | H14: MONTESILVANO | K14: VIA VESTINA 507 | L14: 65015 | M14: MONTESILVANO | N14: PE | Q14: IT | R14: 0854452071 | S14: anna.travaglini60@gmail.com; | T14: - | U14: =VLOOKUP(A:A,'Imprese_File completo'!M:M,1,FALSE) -> TRVNNA60P41F646F
A15: HUXRLU89M51Z210E | B15: IT01A30107S0001 | C15: HU | D15: RULU | E15: F | F15: 11/08/1989 | G15: E | H15: CINA | I15: CN | J15: ITALIA | K15: VIALE TRIVULZIO 3/A | L15: 26845 | M15: CODOGNO | N15: LO | R15: 0377437003 - 3201727118 | S15: rulu1@live.it; | T15: 0021986460001@POSTACERTIFICATA.TABACCAI.IT | U15: =VLOOKUP(A:A,'Imprese_File completo'!M:M,1,FALSE) -> HUXRLU89M51Z210E
A16: MRNMRK92R14H501Q | B16: IT02510C0DS0001 | C16: MARIANI | D16: MIRKO | E16: M | F16: 14/10/1992 | G16: RM | H16: ROMA | K16: VIA LAURENTINA 193 | L16: 00142 | M16: ROMA | N16: RM | P16: SCALA U P. T INT. 2 | Q16: IT | R16: - | S16: - | T16: - | U16: =VLOOKUP(A:A,'Imprese_File completo'!M:M,1,FALSE) -> #N/A
A17: SVRNLT78P46Z129Q | B17: IT02590B04S0001 | C17: SEVERIN | D17: NICOLETA | E17: F | F17: 06/09/1978 | G17: E | H17: ROMANIA | I17: RO | J17: ITALIA | K17: VIA LARIO 5 | L17: 20159 | M17: MILANO | N17: MI | Q17: IT | R17: - | S17: - | T17: - | U17: =VLOOKUP(A:A,'Imprese_File completo'!M:M,1,FALSE) -> #N/A
A18: NTLSFN73D14H501O | B18: IT026A0507S0001 | C18: NATILI | D18: STEFANO | E18: M | F18: 14/04/1973 | G18: RM | H18: ROMA | I18: IT | K18: VIA AUGUSTO CASCIANI 21/A | L18: 00133 | M18: ROMA | N18: RM | R18: 062051691 | S18: - | T18: stefanonatili@pec.it | U18: =VLOOKUP(A:A,'Imprese_File completo'!M:M,1,FALSE) -> NTLSFN73D14H501O
A19: MGGMRA79B14D643U | B19: IT029F0D0AS0001 | C19: MAGGIO | D19: MARIO | E19: M | F19: 14/02/1979 | G19: FG | H19: FOGGIA | K19: PIAZZA NUOVA 17 | L19: 71121 | M19: FOGGIA | N19: FG | Q19: IT | R19: - | S19: - | T19: - | U19: =VLOOKUP(A:A,'Imprese_File completo'!M:M,1,FALSE) -> #N/A
A20: DPENRN82B18F158F | B20: IT02DA0501S0001 | C20: DEPU | D20: ANDREA ANGELO | E20: M | F20: 18/02/1982 | G20: ME | H20: MESSINA | I20: IT | K20: TRAVERSA A DI VIA GAETANO MARTINO 2 | L20: 98039 | M20: TAORMINA | N20: ME | Q20: IT | R20: 3407516929 | S20: andrea.depu@icloud.com; | T20: - | U20: =VLOOKUP(A:A,'Imprese_File completo'!M:M,1,FALSE) -> DPENRN82B18F158F
A21: LNEGRL82H51G273P | B21: IT02E3060DS0001 | C21: LEONE | D21: GABRIELLA GIUSEPPINA | E21: F | F21: 11/06/1982 | G21: PA | H21: PALERMO | I21: IT | K21: VIA GUGLIELMO ALBIMONTE 43 | L21: 90138 | M21: PALERMO | N21: PA | Q21: IT | R21: - | S21: - | T21: - | U21: =VLOOKUP(A:A,'Imprese_File completo'!M:M,1,FALSE) -> #N/A
A22: GRNLCU85B21H490K | B22: IT02E40508S0001 | C22: GRANDINETTI | D22: LUCA | E22: M | F22: 21/02/1985 | G22: CS | H22: ROGLIANO | I22: IT | K22: VIA GUGLIELMO TADDEI 4 | L22: 56124 | M22: PISA | N22: PI | Q22: IT | R22: 3408401653 - 050544511 | S22: lucagrandinetti5@virgilio.it; | T22: tabacchidilucagrandinetti@pec.it | U22: =VLOOKUP(A:A,'Imprese_File completo'!M:M,1,FALSE) -> GRNLCU85B21H490K
A23: NGLCLD68M09H501R | B23: IT031B060ES0001 | C23: ANGELETTI | D23: CLAUDIO | E23: M | F23: 09/08/1968 | G23: RM | H23: ROMA | I23: IT | K23: VIA GIUSEPPE GARIBALDI 10 | L23: 00010 | M23: MONTORIO ROMANO | N23: RM | Q23: IT | R23: 077462216 - 3487423110 | S23: klaudium@tiscali.it; | T23: - | U23: =VLOOKUP(A:A,'Imprese_File completo'!M:M,1,FALSE) -> NGLCLD68M09H501R
A24: BSLGPP86T17L049K | B24: IT03900409S0001 | C24: BASILE | D24: GIUSEPPE | E24: M | F24: 17/12/1986 | G24: TA | H24: TARANTO | I24: IT | K24: VIA ALHAMBRA S.N.. | L24: 74010 | M24: STATTE | N24: TA | R24: 3884449888 | S24: giuseppebasile-86@outlook.it; | T24: - | U24: =VLOOKUP(A:A,'Imprese_File completo'!M:M,1,FALSE) -> BSLGPP86T17L049K
A25: BBTCRL71D30E158P | B25: IT03990F08S0001 | C25: ABBATE | D25: CARLO | E25: M | F25: 30/04/1971 | G25: CE | H25: GRAZZANISE | I25: IT | K25: TRAVERSA I DI VIA ALBERO LUNGO 11 | L25: 81046 | M25: GRAZZANISE | N25: CE | Q25: IT | R25: - | S25: - | T25: - | U25: =VLOOKUP(A:A,'Imprese_File completo'!M:M,1,FALSE) -> #N/A
A26: CHNSNJ63C47Z210Z | B26: IT039A000FS0001 | C26: CHEN | D26: SHENJUAN | E26: F | F26: 07/03/1963 | G26: E | H26: CINA | I26: CN | J26: CINA | K26: VIA ROMA 13 | L26: 26865 | M26: SAN ROCCO AL PORTO | N26: LO | Q26: IT | R26: 3661572683 | S26: susubarmazzini@gmail.com; | T26: chenshenjuan@pec.it | U26: =VLOOKUP(A:A,'Imprese_File completo'!M:M,1,FALSE) -> CHNSNJ63C47Z210Z
A27: LEIFNC77S48C978G | B27: IT03CC0C04S0001 | C27: ELIA | D27: FRANCESCA EMMA | E27: F | F27: 08/11/1977 | G27: LE | H27: COPERTINO | I27: IT | K27: VIA FRA FRANCESCO DA COPERTINO 6 | L27: 73043 | M27: COPERTINO | N27: LE | Q27: IT | R27: - | S27: - | T27: - | U27: =VLOOKUP(A:A,'Imprese_File completo'!M:M,1,FALSE) -> #N/A
A28: FSCNTN74D12D862N | B28: IT03CC0C04S0001 | C28: FIOSCHI | D28: ANTONIO | E28: M | F28: 12/04/1974 | G28: LE | H28: GALATINA | I28: IT | K28: VIA DI SANTA BARBARA SC | L28: 73043 | M28: COPERTINO | N28: LE | Q28: IT | R28: - | S28: - | T28: - | U28: =VLOOKUP(A:A,'Imprese_File completo'!M:M,1,FALSE) -> #N/A
A29: CRNGPP63P27D643F | B29: IT03CF070FS0001 | C29: CORNACCHIO | D29: GIUSEPPE | E29: M | F29: 27/09/1963 | G29: FG | H29: FOGGIA | I29: IT | K29: VIA TOSCANINI 2 | L29: 43029 | M29: TRAVERSETOLO | N29: PR | R29: 0521341225 - 3281783808 | S29: giuseppe_cornacchio@libero.it; | T29: tabaccheriacornacchio@pec.it | U29: =VLOOKUP(A:A,'Imprese_File completo'!M:M,1,FALSE) -> CRNGPP63P27D643F
A30: LRNFRC87C19H793T | B30: IT03E60D0AS0001 | C30: LORENZO | D30: FEDERICO | E30: M | F30: 19/03/1987 | G30: LE | H30: SAN CESARIO DI LECCE | I30: IT | K30: VIA UDINE 20 | L30: 73047 | M30: MONTERONI DI LECCE | N30: LE | Q30: IT | R30: 3387020417 - 3387020417 | S30: chico87lo@hotmail.it; | T30: - | U30: =VLOOKUP(A:A,'Imprese_File completo'!M:M,1,FALSE) -> LRNFRC87C19H793T
A31: BRRCMN68L55L528S | B31: IT03EF0709S0001 | C31: BERARDINELLI | D31: CARMEN | E31: F | F31: 15/07/1968 | G31: SV | H31: VADO LIGURE | I31: IT | K31: VIA VINCENZO BELLINI 3/11 | L31: 17100 | M31: SAVONA | N31: SV | R31: 019-4501359 - 3453259405 | S31: puntosnaisavona@libero.it; | T31: - | U31: =VLOOKUP(A:A,'Imprese_File completo'!M:M,1,FALSE) -> BRRCMN68L55L528S
A32: GMMGPP69D09H163L | B32: IT041C0C09S0001 | C32: GIUMMARRA | D32: GIUSEPPE | E32: M | F32: 09/04/1969 | G32: RG | H32: RAGUSA | I32: IT | K32: VIA IMERA 8 | L32: 97100 | M32: RAGUSA | N32: RG | R32: 0932654419 - 3928600133 | S32: 9351rg@gmail.com; | T32: giummarragiuseppe@pec.webexe.it | U32: =VLOOKUP(A:A,'Imprese_File completo'!M:M,1,FALSE) -> GMMGPP69D09H163L
A33: RLNVNT85D51H501Z | B33: IT041D0A09S0001 | C33: ORLANDI | D33: VALENTINA | E33: F | F33: 11/04/1985 | G33: RM | H33: ROMA | I33: IT | K33: VIA CAULONIA 16 | L33: 00183 | M33: ROMA | N33: RM | Q33: IT | R33: - | S33: - | T33: - | U33: =VLOOKUP(A:A,'Imprese_File completo'!M:M,1,FALSE) -> #N/A
A34: CRODNL90B26H501V | B34: IT045E0702S0001 | C34: CORI | D34: DANIELE | E34: M | F34: 26/02/1990 | G34: RM | H34: ROMA | I34: IT | K34: VIA PIETRAFERRAZZANA 33 | L34: 00131 | M34: ROMA | N34: RM | Q34: IT | R34: - | S34: - | T34: - | U34: =VLOOKUP(A:A,'Imprese_File completo'!M:M,1,FALSE) -> #N/A
A35: TLMNGL81L54A285Q | B35: IT045F0E02S0001 | C35: TOLMINO | D35: ANGELA | E35: F | F35: 14/07/1981 | G35: BT | H35: ANDRIA | I35: IT | K35: VIA ARDIGO' 7 | L35: 76123 | M35: ANDRIA | N35: BT | Q35: IT | R35: - | S35: - | T35: - | U35: =VLOOKUP(A:A,'Imprese_File completo'!M:M,1,FALSE) -> #N/A
A36: MNPRNT60E44F839T | B36: IT0494000FS0001 | C36: MINOPOLI | D36: RENATA | E36: F | F36: 04/05/1960 | G36: NA | H36: NAPOLI | I36: IT | K36: VIA AUGUSTO RIGHI 28 | L36: 80125 | M36: NAPOLI | N36: NA | Q36: IT | R36: 0810360381 - 3278267775 | S36: diocleziano248@libero.it; | T36: minopolirenata@pec.it | U36: =VLOOKUP(A:A,'Imprese_File completo'!M:M,1,FALSE) -> MNPRNT60E44F839T
A37: PCCMTN92P59G141H | B37: IT04E2080ES0001 | C37: PICCIANO | D37: MARTINA | E37: F | F37: 19/09/1992 | G37: CH | H37: ORTONA | I37: IT | K37: VIA ORNI 7 | L37: 66010 | M37: CANOSA SANNITA | N37: CH | R37: - | S37: martinapicciano@gmail.com; | T37: MARTINAPICCIANO@PEC.IT | U37: =VLOOKUP(A:A,'Imprese_File completo'!M:M,1,FALSE) -> PCCMTN92P59G141H
A38: PLVFNC86S20A056I | B38: IT050A0B0ES0001 | C38: PULVIRENTI | D38: FRANCESCO | E38: M | F38: 20/11/1986 | G38: CT | H38: ADRANO | I38: IT | K38: VIA DELLA 35 | L38: 95031 | M38: ADRANO | N38: CT | Q38: IT | R38: 0957692613 - 329-7884065 | S38: pulvirenti.francesco@hotmail.com; | T38: - | U38: =VLOOKUP(A:A,'Imprese_File completo'!M:M,1,FALSE) -> PLVFNC86S20A056I
A39: RLAFNC85H01A717T | B39: IT051E0B0AS0001 | C39: RAELE | D39: FRANCESCO | E39: M | F39: 01/06/1985 | G39: SA | H39: BATTIPAGLIA | I39: IT | K39: VIA CA' BERTACCHI 20/1 | L39: 42030 | M39: VIANO | N39: RE | Q39: IT | R39: 3347854638 | S39: frenzraele@yahoo.it; | T39: - | U39: =VLOOKUP(A:A,'Imprese_File completo'!M:M,1,FALSE) -> RLAFNC85H01A717T
A40: VRDRSO70T66B925K | B40: IT052C0E07S0001 | C40: VERDE | D40: ROSA | E40: F | F40: 26/12/1970 | G40: NA | H40: CASANDRINO | I40: IT | K40: VIA MONTESSORI 14 | L40: 81031 | M40: AVERSA | N40: CE | R40: - | S40: - | T40: - | U40: =VLOOKUP(A:A,'Imprese_File completo'!M:M,1,FALSE) -> VRDRSO70T66B925K
A41: JNIYNG70C25Z210Q | B41: IT054D0404S0001 | C41: JIN | D41: YULIANG | E41: M | F41: 25/03/1970 | H41: ZHEJIANG | I41: CN | K41: VIA TREZZANO 18 | L41: 27029 | M41: VIGEVANO | N41: PV | R41: 3271248771 | S41: YING.CHEN1@ME.COM; | T41: - | U41: =VLOOKUP(A:A,'Imprese_File completo'!M:M,1,FALSE) -> JNIYNG70C25Z210Q
A42: RMNRRT63M08H628A | B42: IT058D0C0CS0001 | C42: ROMANI | D42: ROBERTO | E42: M | F42: 08/08/1963 | G42: RE | H42: RUBIERA | I42: IT | K42: VIA SECCHIA 15/1 | L42: 42048 | M42: RUBIERA | N42: RE | Q42: IT | R42: 0522371281 - 360228668 | S42: enrico.bagnoli@email.it; | T42: romaniroberto1@legalmail.it | U42: =VLOOKUP(A:A,'Imprese_File completo'!M:M,1,FALSE) -> RMNRRT63M08H628A
A43: CCLMRK92R29F152G | B43: IT05CA020ES0001 | C43: COCLITE | D43: MIRKO | E43: M | F43: 29/10/1992 | G43: BR | H43: MESAGNE | I43: IT | K43: VIA SAN MICHELE SALENTINO 20 | L43: 72012 | M43: CAROVIGNO | N43: BR | Q43: IT | R43: 330755050 - 3888154322 | S43: puntocarovigno@hotmail.it; | T43: - | U43: =VLOOKUP(A:A,'Imprese_File completo'!M:M,1,FALSE) -> CCLMRK92R29F152G
A44: DMRGPP57D07A662R | B44: IT061F0609S0001 | C44: DE MARZO | D44: GIUSEPPE | E44: M | F44: 07/04/1957 | G44: BA | H44: BARI | I44: IT | K44: VIA DEGLI ALBERI 26/B | L44: 70010 | M44: CASAMASSIMA | N44: BA | Q44: IT | R44: - | S44: - | T44: - | U44: =VLOOKUP(A:A,'Imprese_File completo'!M:M,1,FALSE) -> #N/A
A45: CRCFRC84D03F205Y | B45: IT065F090CS0001 | C45: CARCANO | D45: FEDERICO | E45: M | F45: 03/04/1984 | G45: MI | H45: MILANO | I45: IT | K45: VIA PAPA GIOVANNI PAOLO II 1 | L45: 20814 | M45: VAREDO | N45: MB | Q45: IT | R45: 3486129161 | S45: federico.carcano@outlook.it; | T45: - | U45: =VLOOKUP(A:A,'Imprese_File completo'!M:M,1,FALSE) -> CRCFRC84D03F205Y
A46: LTMCLD85R63A662R | B46: IT06990609S0001 | C46: ALTAMURA | D46: CLAUDIA | E46: F | F46: 23/10/1985 | G46: BA | H46: BARI | I46: IT | K46: VIA GINO MELDOLESI 36 | L46: 36100 | M46: VICENZA | N46: VI | Q46: IT | R46: 3495517389 | S46: altamuraclaudia@yahoo.it; | T46: - | U46: =VLOOKUP(A:A,'Imprese_File completo'!M:M,1,FALSE) -> LTMCLD85R63A662R
A47: SCRCRL81D20C351J | B47: IT07170F0BS0001 | C47: SCARFIA | D47: CARLO | E47: M | F47: 20/04/1981 | G47: CT | H47: CATANIA | I47: IT | K47: VIA TENENTE GIUSEPPE CATALDO 3 | L47: 95041 | M47: CALTAGIRONE | N47: CT | Q47: IT | R47: 3479449982 | S47: andreascarfia@tiscali.it; | T47: - | U47: =VLOOKUP(A:A,'Imprese_File completo'!M:M,1,FALSE) -> SCRCRL81D20C351J
A48: FNNSMN74B24B354T | B48: IT071B070BS0001 | C48: FANUNZA | D48: SIMONE | E48: M | F48: 24/02/1974 | G48: CA | H48: CAGLIARI | I48: IT | K48: VIA PASTEUR 24 | L48: 08048 | M48: TORTOLI' | N48: NU | Q48: IT | R48: - | S48: - | T48: - | U48: =VLOOKUP(A:A,'Imprese_File completo'!M:M,1,FALSE) -> #N/A
A49: RSLNDR82A07L219O | B49: IT0752020BS0001 | C49: RASULO | D49: ANDREA | E49: M | F49: 07/01/1982 | G49: TO | H49: TORINO | I49: IT | K49: VIA BALTIMORA 49 | L49: 10137 | M49: TORINO | N49: TO | Q49: IT | R49: - | S49: - | T49: - | U49: =VLOOKUP(A:A,'Imprese_File completo'!M:M,1,FALSE) -> #N/A
A50: ZNLDRN62D43I008X | B50: IT07620205S0001 | C50: ZANELLA | D50: ADRIANA | E50: F | F50: 03/04/1962 | G50: PD | H50: SAN MARTINO DI LUPARI | I50: IT | K50: VICOLO MOROSINI 765 | L50: 35010 | M50: SAN GIORGIO IN BOSCO | N50: PD | R50: - | S50: - | T50: - | U50: =VLOOKUP(A:A,'Imprese_File completo'!M:M,1,FALSE) -> ZNLDRN62D43I008X
A51: NTNDNC81H04B519K | B51: IT0764050AS0001 | C51: ANTONECCHIA | D51: DOMENICO | E51: M | F51: 04/06/1981 | G51: CB | H51: CAMPOBASSO | I51: IT | K51: CONTRADA COLLE CALICARE 1 | L51: 86011 | M51: BARANELLO | N51: CB | R51: - | S51: - | T51: - | U51: =VLOOKUP(A:A,'Imprese_File completo'!M:M,1,FALSE) -> #N/A
A52: BLLVNT76D67H501S | B52: IT07930906S0001 | C52: BELLOTTO | D52: VALENTINA | E52: F | F52: 27/04/1976 | G52: RM | H52: ROMA | I52: IT | K52: VIA STRADA DI COLLE PEDESCHIAV 118 | L52: 00018 | M52: PALOMBARA SABINA | N52: RM | Q52: IT | R52: - | S52: - | T52: - | U52: =VLOOKUP(A:A,'Imprese_File completo'!M:M,1,FALSE) -> #N/A
A53: NSTGPP63A28C351A | B53: IT080D0609S0001 | C53: ANASTASI | D53: GIUSEPPE | E53: M | F53: 28/01/1963 | G53: CT | H53: CATANIA | I53: IT | R53: 0957649024 - 3491237592 | S53: giuseppana@tiscali.it; giusappano@tiscali.it | T53: - | U53: =VLOOKUP(A:A,'Imprese_File completo'!M:M,1,FALSE) -> NSTGPP63A28C351A
A54: PRSCRN64L56H785N | B54: IT08980A0ES0001 | C54: PRESTIA | D54: CATERINA | E54: F | F54: 16/07/1964 | G54: VV | H54: SAN CALOGERO | I54: IT | K54: VIA TRAPPETO SNC | L54: 89866 | M54: RICADI | N54: VV | O54: SANTA DOMENICA | Q54: IT | R54: 3476141319 | S54: prestia_cate@icloud.com; | T54: - | U54: =VLOOKUP(A:A,'Imprese_File completo'!M:M,1,FALSE) -> PRSCRN64L56H785N
A55: DLMRST89T43E243B | B55: IT08EC0F0ES0001 | C55: DEL MASTRO | D55: ROSITA | E55: F | F55: 03/12/1989 | G55: CH | H55: GUARDIAGRELE | I55: IT | K55: VIA PARADISO 15 | L55: 66015 | M55: FARA SAN MARTINO | N55: CH | R55: 0872994085 - 3289026378 | S55: rositadelmastro@yahoo.it; | T55: 0024239370001@postacertificata.tabaccai.it | U55: =VLOOKUP(A:A,'Imprese_File completo'!M:M,1,FALSE) -> DLMRST89T43E243B
A56: BRBLST67H09I602R | B56: IT0902060DS0001 | C56: BURBELLO | D56: LUIGI STEFANO | E56: M | F56: 09/06/1967 | G56: MI | H56: SENAGO | I56: IT | K56: VIA MONTE GENEROSO 61 | L56: 22070 | M56: FENEGRO' | N56: CO | Q56: IT | R56: - | S56: - | T56: - | U56: =VLOOKUP(A:A,'Imprese_File completo'!M:M,1,FALSE) -> #N/A
A57: FRRMSM68R03F205F | B57: IT0902060DS0001 | C57: FERRARI | D57: MASSIMO | E57: M | F57: 03/10/1968 | G57: MI | H57: MILANO | I57: IT | K57: VIA CARLO ARMELLINI 7 | L57: 20161 | M57: MILANO | N57: MI | R57: - | S57: - | T57: - | U57: =VLOOKUP(A:A,'Imprese_File completo'!M:M,1,FALSE) -> #N/A
A58: MCCGLC67M11F704F | B58: IT0902060DS0001 | C58: MICCICHE' | D58: GIANLUCA | E58: M | F58: 11/08/1967 | G58: MB | H58: MONZA | I58: IT | K58: VIA NICCOLO' MACHIAVELLI 5 | L58: 20030 | M58: SENAGO | N58: MI | R58: - | S58: - | T58: - | U58: =VLOOKUP(A:A,'Imprese_File completo'!M:M,1,FALSE) -> #N/A
A59: ZRRMRA71S42A604B | B59: IT09430A0AS0001 | C59: ZARRILLO | D59: MARIA | E59: F | F59: 02/11/1971 | G59: PZ | H59: BALVANO | I59: IT | K59: VIA KENNEDY 1 | L59: 20082 | M59: NOVIGLIO | N59: MI | R59: - | S59: - | T59: - | U59: =VLOOKUP(A:A,'Imprese_File completo'!M:M,1,FALSE) -> #N/A
A60: FZAMRC91S05B602Z | B60: IT09EF0407S0001 | C60: FAZIO | D60: MARCO | E60: M | F60: 05/11/1991 | G60: AG | H60: CANICATTI' | I60: IT | K60: CONTRADA SANT'ANNA SNC | L60: 92024 | M60: CANICATTI' | N60: AG | R60: 329-1593037 | S60: faziomarco81@gmail.com; | T60: - | U60: =VLOOKUP(A:A,'Imprese_File completo'!M:M,1,FALSE) -> FZAMRC91S05B602Z
A61: DDDNNL64A70H501F | B61: IT0A0B0401S0001 | C61: DEIDDA | D61: ANTONELLA | E61: F | F61: 30/01/1964 | G61: RM | H61: ROMA | I61: IT | K61: VIA SANTA CROCE DI MAGLIANO 43 | L61: 00131 | M61: ROMA | N61: RM | R61: 0664260272 - 3459708638 | S61: manolitos22@yahoo.com; jotaro81@hotmail.com | T61: - | U61: =VLOOKUP(A:A,'Imprese_File completo'!M:M,1,FALSE) -> DDDNNL64A70H501F
A62: SRMMRN77B10E507K | B62: IT0A160F0ES0001 | C62: SORMANI | D62: MORENO | E62: M | F62: 10/02/1977 | G62: LC | H62: LECCO | I62: IT | K62: VIA MONTE BIANCO 31 | L62: 22040 | M62: BRENNA | N62: CO | Q62: IT | R62: 031797948 - 3407461726 | S62: moreno.sormani@libero.it; | T62: - | U62: =VLOOKUP(A:A,'Imprese_File completo'!M:M,1,FALSE) -> SRMMRN77B10E507K
A63: TRNLRA53L70F356A | B63: IT0A5D0102S0001 | C63: TRONCHIN | D63: LAURA | E63: F | F63: 30/07/1953 | G63: GO | H63: MONFALCONE | K63: VIA ALCIDE DE GASPERI 101 | L63: 34077 | M63: RONCHI DEI LEGIONARI | N63: GO | Q63: IT | R63: - | S63: - | T63: - | U63: =VLOOKUP(A:A,'Imprese_File completo'!M:M,1,FALSE) -> #N/A
A64: LZZVLR88E31B202O | B64: IT0A930C08S0001 | C64: LIUZZO | D64: VALERIO | E64: M | F64: 31/05/1988 | G64: CT | H64: BRONTE | K64: VIA GIOVANNI BATTISTA PERGOLESI 3 | L64: 95034 | M64: BRONTE | N64: CT | Q64: IT | R64: - | S64: - | T64: - | U64: =VLOOKUP(A:A,'Imprese_File completo'!M:M,1,FALSE) -> #N/A
A65: RTTCRD70T16G482Z | B65: IT0B010808S0001 | C65: RIOTTINI PATRIARCA | D65: CORRADO | E65: M | F65: 16/12/1970 | G65: PE | H65: PESCARA | I65: IT | K65: VIALE ALDO MORO 50 | L65: 65015 | M65: MONTESILVANO | N65: PE | Q65: IT | R65: - | S65: - | T65: - | U65: =VLOOKUP(A:A,'Imprese_File completo'!M:M,1,FALSE) -> #N/A
A66: DMRRSO90M63E885K | B66: IT0B150409S0001 | C66: DE MARINIS | D66: ROSA | E66: F | F66: 23/08/1990 | G66: FG | H66: MANFREDONIA | I66: IT | K66: PARCO PADRE PIO 21 | L66: 71030 | M66: ZAPPONETA | N66: FG | Q66: IT | R66: 3333798991 | S66: mattinatabet2@gmail.com; | T66: - | U66: =VLOOKUP(A:A,'Imprese_File completo'!M:M,1,FALSE) -> DMRRSO90M63E885K
A67: MRZMNN94A59M289T | B67: IT0B170101S0001 | C67: MARZATICO | D67: MARIANNA | E67: F | F67: 19/01/1994 | G67: NA | H67: MASSA DI SOMMA | I67: IT | K67: VIA GIOSUE' CARDUCCI 3 | L67: 80040 | M67: VOLLA | N67: NA | Q67: IT | R67: 0815613084 - 3662151131 | S67: giacomo.marzatico@libero.it; | T67: - | U67: =VLOOKUP(A:A,'Imprese_File completo'!M:M,1,FALSE) -> MRZMNN94A59M289T
A68: PPEMTT83E18L425C | B68: IT0B1E070ES0001 | C68: PEPE | D68: MATTEO | E68: M | F68: 18/05/1983 | G68: BA | H68: TRIGGIANO | I68: IT | K68: VIA MONTESANO 107 | L68: 70010 | M68: CAPURSO | N68: BA | Q68: IT | R68: - | S68: - | T68: - | U68: =VLOOKUP(A:A,'Imprese_File completo'!M:M,1,FALSE) -> #N/A
A69: TRTDNL80B01G113I | B69: IT0B620B08S0001 | C69: TRATZI | D69: DANIELE | E69: M | F69: 01/02/1980 | G69: OR | H69: ORISTANO | I69: IT | K69: VICOLO BRANCALEONE DORIA 6 | L69: 09170 | M69: ORISTANO | N69: OR | Q69: IT | R69: - | S69: - | T69: - | U69: =VLOOKUP(A:A,'Imprese_File completo'!M:M,1,FALSE) -> #N/A
A70: TRTGNN85E30G113F | B70: IT0B620B08S0001 | C70: TRATZI | D70: GIOVANNI | E70: M | F70: 30/05/1985 | G70: OR | H70: ORISTANO | I70: IT | K70: VICO DORIA BRANCALEONE 6 | L70: 09170 | M70: ORISTANO | N70: OR | R70: - | S70: - | T70: - | U70: =VLOOKUP(A:A,'Imprese_File completo'!M:M,1,FALSE) -> #N/A
A71: MGGPPL68H30E151R | B71: IT0BAA0101S0001 | C71: MAGGI | D71: PIER PAOLO | E71: M | F71: 30/06/1968 | G71: CO | H71: GRAVEDONA | I71: IT | K71: VIA FILARMONICI 6 | L71: 22018 | M71: PORLEZZA | N71: CO | Q71: IT | R71: +39 335 670 4443 | S71: maggi.pierpaolo@tiscali.it; | T71: - | U71: =VLOOKUP(A:A,'Imprese_File completo'!M:M,1,FALSE) -> MGGPPL68H30E151R
A72: TZONNA85C63F839R | B72: IT0BDC050FS0001 | C72: TOZIO | D72: ANNA | E72: F | F72: 23/03/1985 | G72: NA | H72: NAPOLI | K72: VIA PAPA GIOVANNI XXIII 1 | L72: 20061 | M72: CARUGATE | N72: MI | Q72: IT | R72: - | S72: - | T72: - | U72: =VLOOKUP(A:A,'Imprese_File completo'!M:M,1,FALSE) -> #N/A
A73: LCSCLD82S12G273N | B73: IT0BE70300S0001 | C73: LO CASCIO | D73: CLAUDIO | E73: M | F73: 12/11/1982 | G73: PA | H73: PALERMO | I73: IT | K73: VIA ALIA 7 | L73: 90135 | M73: PALERMO | N73: PA | Q73: IT | R73: - | S73: - | T73: - | U73: =VLOOKUP(A:A,'Imprese_File completo'!M:M,1,FALSE) -> #N/A
A74: ZHOFFE86D10Z210Z | B74: IT0C580400S0001 | C74: ZHOU | D74: FEIFEI | E74: M | F74: 10/04/1986 | G74: E | H74: CINA | I74: CN | J74: CINA | K74: VIA VARESINA 199 | L74: 20156 | M74: MILANO | N74: MI | Q74: IT | R74: - | S74: - | T74: - | U74: =VLOOKUP(A:A,'Imprese_File completo'!M:M,1,FALSE) -> #N/A
A75: CRSPRZ63B55D790S | B75: IT0D180E06S0001 | C75: CRISPINO | D75: PATRIZIA | E75: F | F75: 15/02/1963 | G75: NA | H75: FRATTAMINORE | I75: IT | K75: VIA VENEZIA 10 | L75: 80027 | M75: FRATTAMAGGIORE | N75: NA | Q75: IT | R75: 3345738228 - 3345738228 | S75: rafgar1@libero.it; | T75: crispino63@pec.it | U75: =VLOOKUP(A:A,'Imprese_File completo'!M:M,1,FALSE) -> CRSPRZ63B55D790S
A76: GZZFRZ74T16D403P | B76: IT0D4A090AS0001 | C76: GAZZARRINI | D76: FABRIZIO | E76: M | F76: 16/12/1974 | G76: FI | H76: EMPOLI | I76: IT | K76: VIA R. MORANDI 15 | L76: 50058 | M76: SIGNA | N76: FI | R76: - | S76: - | T76: - | U76: =VLOOKUP(A:A,'Imprese_File completo'!M:M,1,FALSE) -> #N/A
A77: LZZMNL75R12D612Z | B77: IT0D4A090AS0001 | C77: LAZZERINI | D77: MANUELE | E77: M | F77: 12/10/1975 | G77: FI | H77: FIRENZE | I77: IT | K77: VIA NUOVA 34 | L77: 50058 | M77: SIGNA | N77: FI | Q77: IT | R77: - | S77: - | T77: - | U77: =VLOOKUP(A:A,'Imprese_File completo'!M:M,1,FALSE) -> #N/A
A78: GNLMNC84A65B019D | B78: IT0D610409S0001 | C78: GIANELLO | D78: MONICA | E78: F | F78: 25/01/1984 | G78: NO | H78: BORGOMANERO | I78: IT | K78: VIA DON BOSCO 11 SUB A | L78: 13019 | M78: VARALLO | N78: VC | Q78: IT | R78: 3332449223 | S78: MONICA.GIANELLO6@GMAIL.COM; | T78: - | U78: =VLOOKUP(A:A,'Imprese_File completo'!M:M,1,FALSE) -> GNLMNC84A65B019D
A79: SGRLFA65D04C351W | B79: IT0D830704S0001 | C79: SGROI | D79: ALFIO | E79: M | F79: 04/04/1965 | G79: CT | H79: CATANIA | I79: IT | K79: VIA REGINA BIANCA 196 | L79: 95126 | M79: CATANIA | N79: CT | Q79: IT | R79: - | S79: - | T79: - | U79: =VLOOKUP(A:A,'Imprese_File completo'!M:M,1,FALSE) -> #N/A
A80: SPSGPP79L18F839F | B80: IT0D870501S0001 | C80: ESPOSITO | D80: GIUSEPPE | E80: M | F80: 18/07/1979 | G80: NA | H80: NAPOLI | I80: IT | K80: VIA CASTELLO 132 | L80: 80070 | M80: BACOLI | N80: NA | R80: 081-5234010 | S80: peppecentrale@libero.it; | T80: espositogiuseppe2@legalmail.it | U80: =VLOOKUP(A:A,'Imprese_File completo'!M:M,1,FALSE) -> SPSGPP79L18F839F
A81: YNGXMN89S64Z210L | B81: IT0D920207S0001 | C81: YANG | D81: XIAOMIN | E81: F | F81: 24/11/1989 | G81: E | H81: ZHEJIANG | I81: CN | J81: CINA | K81: VIA LAMARMORA 18 | L81: 13866 | M81: MASSERANO | N81: BI | Q81: IT | R81: - | S81: - | T81: - | U81: =VLOOKUP(A:A,'Imprese_File completo'!M:M,1,FALSE) -> #N/A
A82: HUXLHN88L06Z210Z | B82: IT0D940D0BS0001 | C82: HU | D82: LIHUAN | E82: M | F82: 06/07/1988 | G82: E | H82: CINA | I82: CN | J82: CINA | K82: VIA JOHANN KRAVOGL 2 | L82: 39100 | M82: BOLZANO | N82: BZ | Q82: IT | R82: - | S82: - | T82: - | U82: =VLOOKUP(A:A,'Imprese_File completo'!M:M,1,FALSE) -> #N/A
A83: MRNMFR82C52G942N | B83: IT0DA50A04S0001 | C83: MURINO | D83: MARIA FRANCESCA | E83: F | F83: 12/03/1982 | G83: PZ | H83: POTENZA | I83: IT | K83: VIA SAN GIUSEPPE | L83: 85010 | M83: CALVELLO | N83: PZ | R83: - | S83: - | T83: - | U83: =VLOOKUP(A:A,'Imprese_File completo'!M:M,1,FALSE) -> #N/A
A84: PRDGNN75T24B201P | B84: IT0DA50A04S0001 | C84: PARADISO | D84: GIOVANNI | E84: M | F84: 24/12/1975 | G84: PV | H84: BRONI | I84: IT | K84: VIA RIVIERA BOREALE 1 | L84: 85010 | M84: CALVELLO | N84: PZ | R84: - | S84: - | T84: - | U84: =VLOOKUP(A:A,'Imprese_File completo'!M:M,1,FALSE) -> #N/A
A85: CPNDNL72S21L120R | B85: IT0DD20209S0001 | C85: CAPONE | D85: DANILO | E85: M | F85: 21/11/1972 | G85: LT | H85: TERRACINA | I85: IT | K85: CORSO MERIDIONALE 51 | L85: 80143 | M85: NAPOLI | N85: NA | Q85: IT | R85: - | S85: - | T85: - | U85: =VLOOKUP(A:A,'Imprese_File completo'!M:M,1,FALSE) -> CPNDNL72S21L120R
A86: NTNDMN88E13H501B | B86: IT0DEC0400S0001 | C86: ANTONELLI | D86: DAMIANO | E86: M | F86: 13/05/1988 | G86: RM | H86: ROMA | I86: IT | K86: VIA FRANCESCO GENTILE 7 | L86: 00173 | M86: ROMA | N86: RM | Q86: IT | R86: - | S86: - | T86: - | U86: =VLOOKUP(A:A,'Imprese_File completo'!M:M,1,FALSE) -> #N/A
A87: ZZILGU78A05G309E | B87: IT0E160305S0001 | C87: IZZO | D87: LUIGI | E87: M | F87: 05/01/1978 | G87: NA | H87: VILLARICCA | I87: IT | K87: VIA RAFFAELE CARELLI 13 | L87: 80014 | M87: GIUGLIANO IN CAMPANIA | N87: NA | Q87: IT | R87: - | S87: - | T87: - | U87: =VLOOKUP(A:A,'Imprese_File completo'!M:M,1,FALSE) -> #N/A
A88: CFFVCN77A30A089R | B88: IT0E1C0A0AS0001 | C88: CUFFARO | D88: VINCENZO | E88: M | F88: 30/01/1977 | G88: AG | H88: AGRIGENTO | I88: IT | K88: VIALE SICILIA 10 | L88: 92100 | M88: AGRIGENTO | N88: AG | R88: 0922-411657 - 334-2061232 | S88: vincuf@gmail.com; | T88: v.cuffaro@pec.it | U88: =VLOOKUP(A:A,'Imprese_File completo'!M:M,1,FALSE) -> CFFVCN77A30A089R
A89: PLNNDR69R09D007P | B89: IT0E1D0B05S0001 | C89: POLENTA | D89: ANDREA | E89: M | F89: 09/10/1969 | G89: AN | H89: CORINALDO | I89: IT | K89: VIA LUIGI MOTTA 25 | L89: 61032 | M89: FANO | N89: PU | Q89: IT | R89: - | S89: - | T89: - | U89: =VLOOKUP(A:A,'Imprese_File completo'!M:M,1,FALSE) -> #N/A
A90: PTTGNN50T03D345G | B90: IT0E84000ES0001 | C90: PATTERI | D90: GIOVANNI | E90: M | F90: 03/12/1950 | G90: NU | H90: DORGALI | I90: IT | K90: VIA BUDAPEST 8 | L90: 07100 | M90: SASSARI | N90: SS | Q90: IT | R90: - | S90: - | T90: - | U90: =VLOOKUP(A:A,'Imprese_File completo'!M:M,1,FALSE) -> #N/A
A91: LNCMSM70L01D612Z | B91: IT0ECD0707S0001 | C91: LANCIONI | D91: MASSIMILIANO | E91: M | F91: 01/07/1970 | G91: FI | H91: FIRENZE | I91: IT | K91: VIA SETTE REGOLE 11 | L91: 50018 | M91: SCANDICCI | N91: FI | R91: 055753931 - 3382303310 | S91: lancioni@cyberpress.it; | T91: - | U91: =VLOOKUP(A:A,'Imprese_File completo'!M:M,1,FALSE) -> LNCMSM70L01D612Z
A92: DNTGPR65E25L182Y | B92: IT0EE10309S0001 | C92: DANTE | D92: GIAMPIERO | E92: M | F92: 25/05/1965 | G92: RM | H92: TIVOLI | I92: IT | K92: VIA TIBURTINA VALERIA 107 | L92: 00029 | M92: VICOVARO | N92: RM | Q92: IT | R92: 0774492414 - 3478779169 | S92: g.dante@alice.it; | T92: dantegiampiero@pec.it | U92: =VLOOKUP(A:A,'Imprese_File completo'!M:M,1,FALSE) -> DNTGPR65E25L182Y
A93: RGGMME64A41D179O | B93: IT0F060504S0001 | C93: RUGGIERI | D93: EMMA | E93: F | F93: 01/01/1964 | G93: TE | H93: CROGNALETO | I93: IT | K93: VIA GASPERINA 57 | L93: 00118 | M93: ROMA | N93: RM | R93: 0672673062 - 3355775050 | S93: lapergamena.gioco@virgilio.it; | T93: - | U93: =VLOOKUP(A:A,'Imprese_File completo'!M:M,1,FALSE) -> RGGMME64A41D179O
A94: PLTVTR61T07E975Q | B94: IT0F180B00S0001 | C94: PULITI | D94: VALTER | E94: M | F94: 07/12/1961 | G94: PG | H94: MARSCIANO | I94: IT | K94: VIA XXV APRILE 1 | L94: 06055 | M94: MARSCIANO | N94: PG | Q94: IT | R94: - | S94: - | T94: - | U94: =VLOOKUP(A:A,'Imprese_File completo'!M:M,1,FALSE) -> #N/A
A95: ZZRMHL87S12G273J | B95: IT0F2B0F09S0001 | C95: AZZARELLO | D95: MICHELE | E95: M | F95: 12/11/1987 | G95: PA | H95: PALERMO | I95: IT | K95: VIA ROMUALDO GUARNA 1 | L95: 90145 | M95: PALERMO | N95: PA | Q95: IT | R95: 0916818812 - 3294208971 | S95: puntosnaidesaliba@libero.it; | T95: m.azzarello@legalmail.it | U95: =VLOOKUP(A:A,'Imprese_File completo'!M:M,1,FALSE) -> ZZRMHL87S12G273J
A96: MRLFNC72R14G273Y | B96: IT0F4B070CS0001 | C96: AMORELLO | D96: FRANCESCO | E96: M | F96: 14/10/1972 | G96: PA | H96: PALERMO | I96: IT | K96: VIA FILIPPO PECORAINO 18 | L96: 90124 | M96: PALERMO | N96: PA | Q96: IT | R96: 3806379190 | S96: francesco.amorello1@libero.it; | T96: - | U96: =VLOOKUP(A:A,'Imprese_File completo'!M:M,1,FALSE) -> MRLFNC72R14G273Y
A97: MNTLLN58L47A562N | B97: IT0FE9080CS0001 | C97: MANETTI | D97: LILIANA | E97: F | F97: 07/07/1958 | G97: PI | H97: SAN GIULIANO TERME | I97: IT | K97: VIA TONIOLO 40 | L97: 56017 | M97: SAN GIULIANO TERME | N97: PI | O97: MEZZANA | Q97: IT | R97: 050870086 | S97: bonimauri@gmail.com; | T97: lilianamanetti@pec.it | U97: =VLOOKUP(A:A,'Imprese_File completo'!M:M,1,FALSE) -> MNTLLN58L47A562N
A98: LVOMSM59T20G479Y | B98: IT10420D04S0001 | C98: OLIVA | D98: MASSIMO | E98: M | F98: 20/12/1959 | G98: PU | H98: PESARO | I98: IT | K98: VIA ALESSANDRO LAMARMORA 12 | L98: 61122 | M98: PESARO | N98: PU | R98: 0721279089 - 0721279953 | S98: e.vagnini@alice.it; | T98: 0020874270001@POSTACERTIFICATA.TABACCAI.IT | U98: =VLOOKUP(A:A,'Imprese_File completo'!M:M,1,FALSE) -> LVOMSM59T20G479Y
A99: SPSGNR70E18F839U | B99: IT10420E0FS0001 | C99: ESPOSITO | D99: GENNARO | E99: M | F99: 18/05/1970 | G99: NA | H99: NAPOLI | I99: IT | K99: VIA SOLFATARA 38 | L99: 80078 | M99: POZZUOLI | N99: NA | Q99: IT | R99: - | S99: - | T99: - | U99: =VLOOKUP(A:A,'Imprese_File completo'!M:M,1,FALSE) -> #N/A
A100: DSTNLN57S65C351E | B100: IT109D0F0BS0001 | C100: DI STEFANO | D100: NATALINA | E100: F | F100: 25/11/1957 | G100: CT | H100: CATANIA | I100: IT | K100: VIA CADUTI DEL LAVORO 39 | L100: 95030 | M100: GRAVINA DI CATANIA | N100: CT | Q100: IT | R100: 340-5842577 - 3493422737 | S100: natydistefano.57@gmail.com; | T100: - | U100: =VLOOKUP(A:A,'Imprese_File completo'!M:M,1,FALSE) -> DSTNLN57S65C351E
...

Sheet Imprese_File clean
A1: DATI SOCIETA' | X1: DATI RAPPRESENTANTE LEGALE | AM1: CONTATTI
A2: 99 | B2: RAGIONE SOCIALE | C2: _PIVA | D2: _CF | E2: SEDE | F2: Posizione incrociata | G2: Posizione Duplicata | H2: Crif Number | I2: Denominazione | J2: Partita Iva | K2: REA | L2: CCIAA | M2: Codice fiscale | N2: Indirizzo | O2: Cap | P2: Comune | Q2: Frazione | R2: Provincia | S2: Regione | T2: Stato Impresa Cribis | U2: Natura giuridica | V2: Tipo natura giuridica | W2: dummy1 | X2: Cognome Esponente | Y2: Nome Esponente | Z2: Sesso | AA2: Data di nascita | AB2: Provincia di Nascita | AC2: Comune di Nascita | AD2: Nazione di Nascita | AE2: Cittadinanza | AF2: Indirizzo RL | AG2: CAP RL | AH2: Comune RL | AI2: Provincia RL | AJ2: Frazione RL | AK2: Altre indicazioni | AL2: Nazione | AM2: Telefono | AN2: Email | AO2: PEC
A3: 99014890 | B3: BLACK CAFE' DI HU ZHIGE | C3: 02278450396 | D3: HUXZHG73T19Z210Q | F3: Y | H3: ITC7120F00S0001 | I3: BLACK CAFE' DI HU ZHIGE | J3: 02278450396 | K3: 288906 | L3: PV | M3: HUXZHG73T19Z210Q | N3: VIA GAMBOLINA 33 | O3: 27029 | P3: VIGEVANO | R3: PV | S3: LOMBARDIA | T3: Attiva | U3: IMPRESA INDIVIDUALE | V3: IMPRESE INDIVIDUALI | X3: HU | Y3: ZHIGE | Z3: M | AA3: 19/12/1973 | AB3: E | AC3: ZHEJIANG | AD3: CN | AE3: CINA | AF3: VIA AGUZZAFAME 61 | AG3: 27029 | AH3: VIGEVANO | AI3: PV | AJ3: 0 | AK3: 0 | AL3: IT | AM3: 3315003168 | AN3: 1017108343@qq.com; | AO3: -
A4: 99008465 | B4: HAPPY HOUR DI WU SHIJIN | C4: 02594430353 | D4: WUXSJN77E11Z210D | E4: VIA MATTEOTTI 29/B - 42048 RUBIERA RE | F4: Y | H4: ITABEB0B09S0001 | I4: HAPPY HOUR DI WU SHIJIN | J4: 02594430353 | K4: 296066 | L4: RE | M4: WUXSJN77E11Z210D | N4: VIA MATTEOTTI 29/B | O4: 42048 | P4: RUBIERA | R4: RE | S4: EMILIA-ROMAGNA | T4: Attiva | U4: IMPRESA INDIVIDUALE | V4: IMPRESE INDIVIDUALI | X4: WU | Y4: SHIJIN | Z4: M | AA4: 11/05/1977 | AB4: E | AC4: ZHEJIANG | AD4: CN | AE4: CINA | AF4: VIA FRATELLI ROSSELLI 1 | AG4: 42048 | AH4: RUBIERA | AI4: RE | AJ4: 0 | AK4: 0 | AL4: IT | AM4: 0522620048 - 3298482508 | AN4: 104190885@qq.com; | AO4: -
A5: 99015454 | B5: SALA SLOT ROYAL S.R.L. | C5: 02023600477 | D5: 02023600477 | E5: TOSCANA - 51100 PISTOIA | F5: Y | H5: ITA1DA0E04S0001 | I5: SALA SLOT ROYAL SRL | J5: 02023600477 | K5: 604510 | L5: PT | M5: 02023600477 | N5: VIA TOSCANA 124 | O5: 51100 | P5: PISTOIA | R5: PT | S5: TOSCANA | T5: Inattiva | U5: SOCIETA' A RESPONSABILITA' LIMITATA | V5: SOCIETA' DI CAPITALE | X5: JIANG | Y5: JIE | Z5: F | AA5: 02/04/1990 | AB5: E | AC5: CINA | AD5: CN | AE5: CINA | AF5: VIA ANGIOLO BADIANI 12 | AG5: 59100 | AH5: PRATO | AI5: PO | AJ5: 0 | AK5: 0 | AL5: IT | AM5: 3331226767 | AN5: 1135204976@QQ.COM; | AO5: -
A6: 99013944 | B6: LUCKY GAMES DI LIU FANGFANG & C. S.A.S. | C6: 02470750973 | D6: 02470750973 | E6: TOURCOING - 59100 PRATO | F6: Y | H6: IT46550E06S0001 | I6: LUCKY GAMES DI LIU FANGFANG & C. SAS | J6: 02470750973 | K6: 538764 | L6: PO | M6: 02470750973 | N6: VIA TOURCOING 35/4 | O6: 59100 | P6: PRATO | R6: PO | S6: TOSCANA | T6: Attiva | U6: SOCIETA' IN ACCOMANDITA SEMPLICE | V6: SOCIETA' DI PERSONE | X6: LIU | Y6: FANGFANG | Z6: F | AA6: 27/01/1982 | AB6: E | AC6: ZHEJIANG | AD6: CN | AE6: CINA | AF6: VIA AIETTA 20 | AG6: 59016 | AH6: POGGIO A CAIANO | AI6: PO | AJ6: 0 | AK6: 0 | AL6: IT | AM6: 3331226767 | AN6: 1135204976@qq.com; | AO6: -
A7: 99008537 | B7: ZHANG XIANGYANG | C7: 03063650125 | D7: ZHNXGY77P21Z210R | E7: Via Degli Arrotini, 9 - 25016 GHEDI | F7: Y | H7: IT7818090AS0001 | I7: SALA VLT 168 DI ZHANG XIANGYANG | J7: 03063650125 | K7: 521553 | L7: PO | M7: ZHNXGY77P21Z210R | N7: VIA LIGURIA 6/5 | O7: 59100 | P7: PRATO | R7: PO | S7: TOSCANA | T7: Attiva | U7: IMPRESA INDIVIDUALE | V7: IMPRESE INDIVIDUALI | X7: ZHANG | Y7: XIANGYANG | Z7: M | AA7: 21/09/1977 | AB7: E | AC7: ZHEJIANG | AD7: CN | AE7: CINA | AF7: VIA FABIO FILZI 116 | AG7: 59100 | AH7: PRATO | AI7: PO | AJ7: 0 | AK7: 0 | AL7: IT | AM7: 3331226767 | AN7: 1135204976@qq.com; | AO7: -
A8: 99001076 | B8: TABACCHERIA ORSINI TIZIANA | C8: 01450380686 | D8: RSNTZN73A43L186L | E8: VIA VESTINA 152 - 65016 MONTESILVANO PE | F8: Y | H8: ITB8640602S0001 | I8: ORSINI TIZIANA | J8: 01450380686 | K8: 101847 | L8: PE | M8: RSNTZN73A43L186L | N8: VIA VESTINA 152 | O8: 65015 | P8: MONTESILVANO | R8: PE | S8: ABRUZZO | T8: Attiva | U8: IMPRESA INDIVIDUALE | V8: IMPRESE INDIVIDUALI | X8: ORSINI | Y8: TIZIANA | Z8: F | AA8: 03/01/1973 | AB8: PE | AC8: TOCCO DA CASAURIA | AD8: IT | AE8: 0 | AF8: VIA RIGOPIANO 173/7 | AG8: 65124 | AH8: PESCARA | AI8: PE | AJ8: 0 | AK8: 0 | AL8: 0 | AM8: 0854680144 | AN8: tizianaorsini99@tiscali.it; | AO8: 0010021530001@postacertificata.tabaccai.it
A9: 99000841 | B9: CARESTIA ANTONIO | C9: 01284980685 | D9: CRSNTN68B19G482R | E9: c/so Primo Maggio 141/143 - 65027 Scafa PE | F9: Y | H9: IT8B4F0909S0001 | I9: CARESTIA ANTONIO | J9: 01284980685 | K9: 90053 | L9: PE | M9: CRSNTN68B19G482R | N9: CORSO I MAGGIO 141/143 | O9: 65027 | P9: SCAFA | R9: PE | S9: ABRUZZO | T9: Attiva | U9: IMPRESA INDIVIDUALE | V9: IMPRESE INDIVIDUALI | X9: CARESTIA | Y9: ANTONIO | Z9: M | AA9: 19/02/1968 | AB9: PE | AC9: PESCARA | AD9: IT | AE9: 0 | AF9: VIA BOLOGNA 13 | AG9: 65027 | AH9: SCAFA | AI9: PE | AJ9: 0 | AK9: 0 | AL9: IT | AM9: 0858542105 - 0858542105 | AN9: antonio.carestia68@gmail.com; | AO9: 0010312280001@postacertificata.tabaccai.it
A10: 99001601 | B10: MARCO LERA | C10: 01847300462 | D10: LREMRC71D23E715R | E10: VIA DELLE VILLE 67/A - 55013 LAMMARI LU | F10: Y | H10: IT6500070ES0001 | I10: LERA MARCO | J10: 01847300462 | K10: 177009 | L10: LU | M10: LREMRC71D23E715R | N10: VIA DELLE VILLE 67/A | O10: 55012 | P10: CAPANNORI | Q10: LAMMARI | R10: LU | S10: TOSCANA | T10: Attiva | U10: IMPRESA INDIVIDUALE | V10: IMPRESE INDIVIDUALI | X10: LERA | Y10: MARCO | Z10: M | AA10: 23/04/1971 | AB10: LU | AC10: LUCCA | AD10: IT | AE10: 0 | AF10: VIA LOMBARDA 145 LAMMARI | AG10: 55012 | AH10: CAPANNORI | AI10: LU | AJ10: 0 | AK10: 0 | AL10: 0 | AM10: 0583961657 | AN10: ricevitoria.osteria@libero.it; | AO10: 0010373400001@postacertificata.tabaccai.it
A11: 99007528 | B11: MARTINO 2000 | C11: 02359340961 | D11: RGGCDM57E22D231T | E11: VIALE COOPERAZIONE, 43 - 20095 CUSANO MILANINO | F11: Y | H11: ITBE86070DS0001 | I11: MARTINO 2000 | J11: 02359340961 | K11: 1439199 | L11: MI | M11: RGGCDM57E22D231T | N11: VIALE COOPERAZIONE 54 | O11: 20095 | P11: CUSANO MILANINO | R11: MI | S11: LOMBARDIA | T11: Attiva | U11: IMPRESA INDIVIDUALE | V11: IMPRESE INDIVIDUALI | X11: ORIGGI | Y11: CLAUDIO MARIA | Z11: M | AA11: 22/05/1957 | AB11: MI | AC11: CUSANO MILANINO | AD11: IT | AE11: 0 | AF11: VIA CARLO IMBONATI 62/2 | AG11: 20159 | AH11: MILANO | AI11: MI | AJ11: 0 | AK11: 0 | AL11: IT | AM11: 0266401122 - 3355202677 | AN11: claudio@martino2000.it; | AO11: 0010398410001@POSTACERTIFICATA.TABACCAI.IT; fe.dylogbuffetti@sicurezzapostale.it
A12: 99000759 | B12: CERQUA MASSIMILIANOTABACCHERIA RIV. | C12: 01218970505 | D12: CRQMSM72M03B950G | E12: PIAZZA MAZZINI 14 - 50010 MIGLIARINO PISANO PI | F12: Y | H12: IT69C40105S0001 | I12: CERQUA MASSIMILIANO | J12: 01218970505 | K12: 108217 | L12: PI | M12: CRQMSM72M03B950G | N12: PIAZZA GIUSEPPE MAZZINI 12 | O12: 56019 | P12: VECCHIANO | R12: PI | S12: TOSCANA | T12: Attiva | U12: IMPRESA INDIVIDUALE | V12: IMPRESE INDIVIDUALI | X12: CERQUA | Y12: MASSIMILIANO | Z12: M | AA12: 03/08/1972 | AB12: PI | AC12: CASCINA | AD12: IT | AE12: 0 | AF12: VIA CHARLES DARWIN 2 ARENA METATO | AG12: 56017 | AH12: SAN GIULIANO TERME | AI12: PI | AJ12: 0 | AK12: 0 | AL12: 0 | AM12: 050803320 - 3488235512 | AN12: maxcerqua@yahoo.it; | AO12: 0020046200001@POSTACERTIFICATA.TABACCAI.IT

Sheet voucher
A1: voucher | B1: partita iva (account/codice sap) | C1: rappresentante legale | D1: pec | E1: telefono | F1: data invio | G1: data attivazione | H1: stato
A2: WS935-QA8WE2WTQH
A3: WS935-4VXQ6AJY6L
A4: WS935-LCFJUDG4TW
A5: WS935-KRGH9EIP9C
A6: WS935-TJLAYIGDPM
A7: WS935-138C8N1DK5
A8: WS935-OLCPVVB6WC
A9: WS935-CAC1W7UVUK
A10: WS935-OWU0STYO2G
A11: WS935-AXQ1NX45SQ
A12: WS935-90VM68BAUF
A13: WS935-6Q21QYPVEB
... A1738: WS935-TBYTYKJ9NJ

Sheet Giacomo1
A1: EMAIL | B1: PEC | C1: VOUCHER
B2: 0022156710001@postacertificata.tabaccai.it | C2: WS935-M2X6XX9519
B3: 7stellesas@pec.it | C3: WS935-XBGV3XK9CN
B4: abelloplay@pec.it | C4: WS935-9C0S4S6Y2I
B5: BAR.ITALIA_SNC@PEC.IT | C5: WS935-RMV6PQKJT0
B6: CAMPI.FLAVIO@LEGALMAIL.IT | C6: WS935-E0D89UCEX5
B7: catalanofrancesco84@pec.it | C7: WS935-FVSVVCPB2X
B8: ciampisnc@sicurezzapostale.it | C8: WS935-RKQ9IM3QHC
B9: CICABETSRL@LEGALMAIL.IT | C9: WS935-Y60X3X6V76
B10: dega@legalmail.it | C10: WS935-TRR15J9AE8
B11: depalmavincenzo88@pec.it | C11: WS935-PAR03FBTXF
B12: F.CARACCI77@ARUBAPEC.IT | C12: WS935-D2EC7YA916
B13: f.llilamasrls@pec.it | C13: WS935-O2GM3UMXIU
... B44: TOTALGEST@LEGALMAIL.IT | C44: WS935-VX118U6O7N
A45: 0245486444@fastwebnet.it | B45: BIEMME@PECIMPRESE.IT | C45: WS935-JOX4Y0WHE2
A46: 1017108343@qq.com | C46: WS935-QA8WE2WTQH
A47: 104190885@qq.com | C47: WS935-4VXQ6AJY6L
A48: 1135204976@QQ.COM | C48: WS935-KRGH9EIP9C
A49: 1135204976@qq.com | C49: WS935-TJLAYIGDPM
A50: 1135204976@qq.com | C50: WS935-OWU0STYO2G
A51: 1692774133@qq.com | C51: WS935-90VM68BAUF
A52: 2015magiasrl@gmail.com | B52: 2015MAGIASRL@PEC.IT | C52: WS935-WTTSQYH36D
A53: 3358186977@virgilio.it | B53: ALMASRL@LEGALPEC.ME | C53: WS935-H6T2RBHHGY
A54: 3lettie@tiscali.it | B54: PUNTOSNAI.VENTIMIGLIA@LEGALMAIL.IT | C54: WS935-UDRPKO826N
A55: 443447131@qq.com | C55: WS935-SEPTWDG815
A56: 48581587@qq.com | C56: WS935-6Q21QYPVEB
A57: 4winsrl@gmail.com | B57: 4WINSRL@LEGALMAIL.IT | C57: WS935-44AU5455YR
A58: 510658306@qq.com | C58: WS935-JE5EME3G10
A59: 51mtoro@libero.it | C59: WS935-3L2V6A6W8U
A60: 525215546@qq.com | C60: WS935-MWW6XUXWC0
A61: 6unica1@virgilio.it | B61: VANNI.MIRKO@LEGALMAIL.IT | C61: WS935-OH5IX5QSFA
A62: 88huanglihong@gmail.com | B62: huanglihong@pec.it | C62: WS935-U9NYRJ231D
A63: 8games@tiscali.it | B63: 8GAMESSRL@LEGALMAIL.IT | C63: WS935-WV8HIVXCYX
A64: 9351rg@gmail.com | B64: giummarragiuseppe@pec.webexe.it | C64: WS935-OSKR5816HP
A65: a.tagliasacchi@alice.it | B65: MINIBARSNC@LEGALMAIL.IT | C65: WS935-GC2GDXY9J4
A66: a3880557673@gmail.com | B66: allpubsnc@pec.it | C66: WS935-BR1OF7M4M9
A67: achilleesposito@hotmail.it | C67: WS935-W53YJ9T3M9
A68: adamofilippo@libero.it | B68: ROYALPLANET@PEC.IT | C68: WS935-SVTVXM26T8
A69: adele.guerriero@libero.it | C69: WS935-S6N7XLW0PW
A70: adm_csnai@yahoo.it | B70: GOODLUCKSRL@PEC.IT | C70: WS935-BWSKXNOV81
A71: ag.emme3@gmail.com | B71: agenziam3@pcert.postecert.it | C71: WS935-6GKA98J51T
A72: agararancini@it.cirsa.com | B72: italtronic@pec.it | C72: WS935-EX2USVVL4F
A73: agenzia.bettercagliari@gmail.com | B73: betteritaliasrl@pec.it | C73: WS935-VVWARGXHKX
A74: agenzia.ginosa@libero.it | C74: WS935-4FS5MW8O5Y
A75: agenzia3224@gmail.com | C75: WS935-X97QK3UGLO
A76: agenziaallgames@gmail.com | B76: ALLGAMES.CERESAM@LEGALMAIL.IT | C76: WS935-J4U9CFLVM7
A77: agenziacesenatico@virgilio.it | B77: AGENZIASCOMMESSE@ARUBAPEC.IT | C77: WS935-W9G4MFEF73
A78: agenziaexpress2004@gmail.com | C78: WS935-L5L5C3U3L5
A79: agenziagiordano326@hotmail.com | C79: WS935-X6UESKE0XO
A80: agenziaippicajovinelli@virgilio.it | B80: AGENZIAIPPICAJOVINELLI@PEC.IT | C80: WS935-BXR82QUGBM
A81: agenziamarconi.gc@libero.it | B81: vian-srl@gigapec.it | C81: WS935-CN8BQ906O2
A82: agenziaromasrl@tiscali.it | B82: AGENZIAROMASRL@LEGALMAIL.IT | C82: WS935-37J0IOC03U
A83: agenziasnaibarcellonapg@gmail.com | B83: annagioianotarianni@pec.it | C83: WS935-8HU6KORPE4
A84: agenziasnaipavia@gmail.com | C84: WS935-OQCHA56560
A85: agenziaviareggio@gmail.com | C85: WS935-IIJ2K47JX1
A86: ageopera@outlook.it | C86: WS935-UO3SU388KF
A87: agofio@hotmail.it | C87: WS935-V2FX978R61
A88: agostinomanzi68@libero.it | C88: WS935-2CEXHO6XUP
A89: agropolisnai@gmail.com | C89: WS935-P8QTVX5XF0
A90: albanopanetta@gmail.com | C90: WS935-GN2T354RQ4
A91: alberto.menichini@gmail.com | B91: alberto.menichini@pec.it | C91: WS935-4NE3O5DGSH
A92: albertomartinelli.lume@hotmail.com | C92: WS935-7TXN99PAX8
A93: Ale.nava1996@icloud.com | C93: WS935-M8JHF97ICP
A94: alehe1688@icloud.com | C94: WS935-LKGUH3OEH9
A95: alessandrapollastrini72@gmail.com | B95: alessandrapollastrini72@pec.it | C95: WS935-I5BDP4DWQ9
A96: alessandrascara_2018@libero.it | C96: WS935-P91TSJ4YKI
A97: alessandro.frigerio@wingaming.it | B97: WINGAMING@LEGALMAIL.IT | C97: WS935-NA868GUROK
A98: alessandro.lombardi.b@gmail.com | C98: WS935-9RNDTXWBY0
A99: alessandro.messina@pec.odcec.ct.it | B99: Chioscodellavittoria@pec.it | C99: WS935-TXOFL69VDV
A100: alessandro.panno84@gmail.com | C100: WS935-Y4P360T2II
A101: alessandrolucafone@icloud.com | C101: WS935-B4BWCMRQL8
A102: alessandromicheli64@virgilio.it | B102: ALESSANDRO.MICHELI@PEC.LOTTOMATICA.IT | C102: WS935-RX2DVX7DGD
A103: alessandroviti96@gmail.com | C103: WS935-15YPAFEU5D
A104: alessiahu86@hotmail.com | C104: WS935-URX2E5HJM9
A105: alessiahu86@hotmail.com | C105: WS935-N8LPP7S06O
A106: alessiahu86@hotmail.com | C106: WS935-KJVJG5QM65
A107: alessio.hu.2001@gmail.com | C107: WS935-59WVWUMTSA
A108: alessiohaiyan@hotmail.com | C108: WS935-PRM7JYS7TR
A109: alessiorizzelli@libero.it | B109: alessiorizzelli@pec.it | C109: WS935-ENFXBMYX5C
A110: alessiosuppressa@virgilio.it | C110: WS935-IYBOTELLUL
A111: alex.nicolosi@hotmail.it | B111: ALEX.NICOLOSI@PEC.IT | C111: WS935-5VHGAX7LQA
A112: alex-cra@hotmail.it | C112: WS935-KK09T70XMV
A113: alexdelli83@libero.it | C113: WS935-NJJEXMOUMP
A114: alexpot85@libero.it | C114: WS935-OLCPVVB6WC
A115: alexshine92@gmail.com | C115: WS935-3VENW7TKKV
A116: alfie80@alice.it | B116: ALFREDO.PIAZZI@PEC.IT | C116: WS935-AY98PGG5EF
A117: alfonsopappacena97@libero.it | C117: WS935-WPXGLCIVFN
A118: alfredo.bazzano@yahoo.it | C118: WS935-4FM8TXRQYU
A119: alfredoricci.ip@virgilio.it | C119: WS935-G1RQHMJQ26
A120: aliberti.mel73@gmail.com | C120: WS935-G5SV8J2J4H
A121: alice.otto@progettostudio.legalmail.it | C121: WS935-1QN5A35N66
A122: alium2021@libero.it | C122: WS935-ITXESU5TJ4
A123: allegretti.group@gmail.com | B123: superbetsrl@pec.it | C123: WS935-XC30XT6GRA
A124: allegrettif85@gmail.com | B124: FADO-SRL@LEGALMAIL.IT | C124: WS935-B5X1IV13KF
A125: allinsalagiochi@gmail.com | B125: SASALLIN@PEC.IT | C125: WS935-J8XO2UIOJU
A126: almaracafe@katamail.com | B126: ALMARA@PCERT.POSTECERT.IT | C126: WS935-G91EP79XPE
A127: altamuraclaudia@yahoo.it | C127: WS935-1VXQ772T60
A128: am.bartabacchi@libero.it | C128: WS935-GBFX28VXFK
A129: amal.srl.pineta@gmail.com | C129: WS935-CH9768T2GF
A130: amarantoslot@outlook.it | B130: AMARANTOSLOT@PEC.IT | C130: WS935-UYU0D4YO02
...

Sheet Giacomo2
A1: EMAIL | B1: VOUCHER
A2: 0010021530001@postacertificata.tabaccai.it | B2: WS935-QC6LBBBVJ1
A3: 0010312280001@postacertificata.tabaccai.it | B3: WS935-SQSVPXGISA
A4: 0010373400001@postacertificata.tabaccai.it | B4: WS935-854QP5NAK5
A5: 0010398410001@POSTACERTIFICATA.TABACCAI.IT | B5: WS935-7JDAHA1OXU
A6: 0020046200001@POSTACERTIFICATA.TABACCAI.IT | B6: WS935-S6T3E94B2X
A7: 0020067730001@POSTACERTIFICATA.TABACCAI.IT | B7: WS935-X93Q7QLURI
A8: 0020117990001@postacertificata.tabaccai.it | B8: WS935-XUV8EVBCIW
A9: 0020149420001@postacertificata.tabaccai.it | B9: WS935-1IE66BJF7W
A10: 0020259480001@postacertificata.tabaccai.it | B10: WS935-BVIQLL6RX1
A11: 0020552590001@postacertificata.tabaccai.it | B11: WS935-UTLBMYQY6W
A12: 0020681610001@postacertificata.tabaccai.it | B12: WS935-TY57A9S5DA
... A1738: zzyfran@gmail.com | B1738: WS935-RJMJTUYVRS
